[{"Id":22284,"ImgUrl":"http://img.jingtuitui.com/2702c201712270423369238.jpg","Name":"羽绒棉服女短款韩版冬装大毛领连帽棉衣 时尚修身加厚","Introduce":"优质羽绒棉服，加厚保暖，实物拍摄，质量保证，款式时尚百搭。","OldPrice":199.0000,"CouponMoney":70.0000,"CommissionRate":0.200,"ShopTypeId":1,"PeiSongType":"京东","InsertTime":"2017-12-27T16:39:58.297","url":"https://union-click.jd.com/jdc?d=zziexk","uid":"1000000078","pid":"1113721487","shopid":22284,"shijiancha":168},{"Id":22277,"ImgUrl":"http://img14.360buyimg.com/imgzone/jfs/t16216/196/719206559/532513/5a211e9f/5a3b819bN8ddf0e4e.jpg","Name":"婴儿衣服0-1.5岁宝宝外出服","Introduce":"新生儿保暖必备，秋冬加厚，防风保暖，送礼佳品","OldPrice":149.0000,"CouponMoney":70.0000,"CommissionRate":0.200,"ShopTypeId":4,"PeiSongType":"京东","InsertTime":"2017-12-27T16:39:58.237","url":"https://union-click.jd.com/jdc?d=D4PIUk","uid":"1000000078","pid":"1113721487","shopid":22277,"shijiancha":168},{"Id":22273,"ImgUrl":"http://img14.360buyimg.com/imgzone/jfs/t13159/71/2457899610/756313/719b6395/5a41083fNa58470f9.jpg","Name":"【潮流百搭】吉马克 牛津纺休闲衬衫","Introduce":"四大品质，精工细作，免烫 ！不起球！纯色百搭衬衫，多色可选，怎么搭都好看，男神的最爱！","OldPrice":89.0000,"CouponMoney":40.0000,"CommissionRate":0.300,"ShopTypeId":2,"PeiSongType":"京东","InsertTime":"2017-12-27T16:39:58.13","url":"https://union-click.jd.com/jdc?d=dcgy1n","uid":"1000000078","pid":"1113721487","shopid":22273,"shijiancha":168},{"Id":22270,"ImgUrl":"http://img.jingtuitui.com/0b0dd201712271519319088.jpg","Name":"春节拉花 春字福字无纺布喜庆拉花","Introduce":"春节拉花 过年客厅房间装饰布置无纺布春字拉花店铺喜庆福拉花3米 4条装","OldPrice":46.0000,"CouponMoney":10.0000,"CommissionRate":0.200,"ShopTypeId":7,"PeiSongType":"京东","InsertTime":"2017-12-27T16:00:01.457","url":"https://union-click.jd.com/jdc?d=hRi9Wp","uid":"1000000078","pid":"1113721487","shopid":22270,"shijiancha":168},{"Id":22268,"ImgUrl":"http://img14.360buyimg.com/imgzone/jfs/t9934/319/981499721/467182/afe9d756/59daeca2N8ecce21d.jpg","Name":"中老年女装冬装 针织衫加厚保暖妈妈装","Introduce":"年终大促 中年女装加厚内里加绒保暖针织衫 面料舒适 质量保证","OldPrice":178.0000,"CouponMoney":30.0000,"CommissionRate":0.200,"ShopTypeId":1,"PeiSongType":"京东","InsertTime":"2017-12-27T15:59:58.337","url":"https://union-click.jd.com/jdc?d=VWRwPc","uid":"1000000078","pid":"1113721487","shopid":22268,"shijiancha":169},{"Id":22251,"ImgUrl":"http://img.jingtuitui.com/d0cd2201712271153236762.jpg","Name":" 原装数据线闪电快充数据线手机充电器线/安卓苹果通用","Introduce":"ecclus艾克拉斯 原装数据线 Type-C闪电快充数据线/手机充电器线/安卓充电线 1.2米【支持快充】白色 通用 华为P9mate9荣耀89小米5x64c乐视","OldPrice":19.9000,"CouponMoney":14.0000,"CommissionRate":0.200,"ShopTypeId":11,"PeiSongType":"京东","InsertTime":"2017-12-27T15:55:44.427","url":"https://union-click.jd.com/jdc?d=evdkO6","uid":"1000000078","pid":"1113721487","shopid":22251,"shijiancha":169},{"Id":22244,"ImgUrl":"http://img.jingtuitui.com/ffcb6201712271417076651.jpg","Name":"家用扫地机器人APP操控陀螺仪导航自控水箱智能规划式","Introduce":"购机赠边刷/滤网x1！APP操控、陀螺仪导航、自控水箱、智能规划式、进口玻璃镜面、Turbo直线加速高效规划清扫、大尘盒静音王\n","OldPrice":1499.0000,"CouponMoney":511.0000,"CommissionRate":0.200,"ShopTypeId":11,"PeiSongType":"京东","InsertTime":"2017-12-27T15:55:44.41","url":"https://union-click.jd.com/jdc?d=9CnEOz","uid":"1000000078","pid":"1113721487","shopid":22244,"shijiancha":169},{"Id":22208,"ImgUrl":"http://img.jingtuitui.com/fa170201712271129217977.jpg","Name":"【送运费险】户外加厚保暖野营睡袋","Introduce":"选择我们，拒绝失眠！舒适面料，健康环保，款式多样，有它，每一晚都能安心睡眠！","OldPrice":79.0000,"CouponMoney":30.0000,"CommissionRate":0.200,"ShopTypeId":9,"PeiSongType":"京东","InsertTime":"2017-12-27T15:55:41.86","url":"https://union-click.jd.com/jdc?d=DY2p9W","uid":"1000000078","pid":"1113721487","shopid":22208,"shijiancha":169},{"Id":22204,"ImgUrl":"http://img14.360buyimg.com/imgzone/jfs/t14536/11/715713983/585491/d18e0acc/5a35cee7N86625142.jpg","Name":"盛源 户外帐篷多人手抛自动帐速开露营帐篷双门","Introduce":"1秒一抛即开，方便迅速，双开门设计，防泼水面料可防小雨，适合休闲野营，2种容量大小","OldPrice":99.0000,"CouponMoney":20.0000,"CommissionRate":0.200,"ShopTypeId":9,"PeiSongType":"京东","InsertTime":"2017-12-27T15:55:41.857","url":"https://union-click.jd.com/jdc?d=6G2gFS","uid":"1000000078","pid":"1113721487","shopid":22204,"shijiancha":169},{"Id":22205,"ImgUrl":"http://img14.360buyimg.com/imgzone/jfs/t10672/313/2231346684/488860/9b142360/59f1e5b1N4260615a.png","Name":"探拓  户外速干T恤男女长袖圆领轻薄透气速干衣宽松大码","Introduce":"探拓- 专业做户外服饰品牌，情侣款速干T恤，吸湿排汗，透气速干高弹性!","OldPrice":59.0000,"CouponMoney":20.0000,"CommissionRate":0.200,"ShopTypeId":9,"PeiSongType":"京东","InsertTime":"2017-12-27T15:55:41.857","url":"https://union-click.jd.com/jdc?d=N3bYPQ","uid":"1000000078","pid":"1113721487","shopid":22205,"shijiancha":169},{"Id":22207,"ImgUrl":"http://img.jingtuitui.com/e9291201712271154363839.jpg","Name":"户外尖峰旅行背包双肩登山包男女休闲背包40L彩黑色","Introduce":"背部立体透气网布背负设计、背部透气通风，精选优质材质，大容量，简约潮流，多功能组合，专业的空气导流设计，排汗减压抗震，负重不变形","OldPrice":89.0000,"CouponMoney":40.0000,"CommissionRate":0.200,"ShopTypeId":9,"PeiSongType":"京东","InsertTime":"2017-12-27T15:55:41.857","url":"","uid":"1000000078","pid":"1113721487","shopid":22207,"shijiancha":169},{"Id":22202,"ImgUrl":"http://img14.360buyimg.com/imgzone/jfs/t15436/118/1032991980/332571/87c4a32b/5a41fa8bNd7b98758.jpg","Name":"韩版印花铆钉双肩包旅行背包","Introduce":"冬季新款女士双肩包韩版时尚印花铆钉背包旅行包包，经典时尚百搭款，原价99，券后79！","OldPrice":99.0000,"CouponMoney":20.0000,"CommissionRate":0.200,"ShopTypeId":8,"PeiSongType":"京东","InsertTime":"2017-12-27T15:55:41.817","url":"https://union-click.jd.com/jdc?d=3lZSKX","uid":"1000000078","pid":"1113721487","shopid":22202,"shijiancha":169},{"Id":22203,"ImgUrl":"http://img14.360buyimg.com/imgzone/jfs/t12439/339/2536759882/219748/6cd1626e/5a4304a1N7d256233.jpg","Name":"石末（SHIMO）休闲鞋","Introduce":"生活一天天继续，生活圈住的是我们的视野和脚步，圈不住的是对自由无限渴望—— ——石末（SHIMO）休闲鞋","OldPrice":695.0000,"CouponMoney":500.0000,"CommissionRate":0.200,"ShopTypeId":8,"PeiSongType":"京东","InsertTime":"2017-12-27T15:55:41.817","url":"https://union-click.jd.com/jdc?d=vPEkqC","uid":"1000000078","pid":"1113721487","shopid":22203,"shijiancha":169},{"Id":22201,"ImgUrl":"http://img14.360buyimg.com/imgzone/jfs/t14452/245/845771274/112106/2f143dd2/5a3b6389N5e929bdb.jpg","Name":"中学生书包女韩版波点小狗印花双肩包小学生书包两件套","Introduce":"领券直降10，赠送运费险，支持7天无理由退换！品牌书包，质量保证！","OldPrice":59.0000,"CouponMoney":10.0000,"CommissionRate":0.300,"ShopTypeId":8,"PeiSongType":"京东","InsertTime":"2017-12-27T15:55:41.807","url":"https://union-click.jd.com/jdc?d=443IY9","uid":"1000000078","pid":"1113721487","shopid":22201,"shijiancha":169},{"Id":22198,"ImgUrl":"http://img14.360buyimg.com/imgzone/jfs/t11647/140/2500348195/454163/ac03e30c/5a192dc6N6249fd04.jpg","Name":"小学生减负双肩包学生书包","Introduce":"如京 小学生书包女2-4-6年级儿童减负双肩包女韩版时尚卡通大容量背包，减负书包，原价89，券后59！","OldPrice":89.0000,"CouponMoney":30.0000,"CommissionRate":0.200,"ShopTypeId":8,"PeiSongType":"京东","InsertTime":"2017-12-27T15:55:41.803","url":"https://union-click.jd.com/jdc?d=U7H2Xo","uid":"1000000078","pid":"1113721487","shopid":22198,"shijiancha":169},{"Id":22199,"ImgUrl":"http://img14.360buyimg.com/imgzone/jfs/t16414/72/887375436/211291/29f51e57/5a420801Nd4b25f79.jpg","Name":"新款磨砂单肩包休闲手提包","Introduce":"2017新款磨砂单肩包休闲百搭女士手提包经典纯色包包，经典纯色设计，原件99，券后79！","OldPrice":99.0000,"CouponMoney":20.0000,"CommissionRate":0.200,"ShopTypeId":8,"PeiSongType":"京东","InsertTime":"2017-12-27T15:55:41.803","url":"https://union-click.jd.com/jdc?d=rqOV9Q","uid":"1000000078","pid":"1113721487","shopid":22199,"shijiancha":169},{"Id":22200,"ImgUrl":"http://img14.360buyimg.com/imgzone/jfs/t15244/226/1019257886/141264/f0d11c40/5a4305d6N46adad59.jpg","Name":"石末（SHIMO）休闲鞋","Introduce":"生活一天天继续，生活圈住的是我们的视野和脚步，圈不住的是对自由无限渴望—— ——石末（SHIMO）休闲鞋","OldPrice":612.0000,"CouponMoney":419.0000,"CommissionRate":0.200,"ShopTypeId":8,"PeiSongType":"京东","InsertTime":"2017-12-27T15:55:41.803","url":"https://union-click.jd.com/jdc?d=EwNv9i","uid":"1000000078","pid":"1113721487","shopid":22200,"shijiancha":169},{"Id":22194,"ImgUrl":"http://img14.360buyimg.com/imgzone/jfs/t15805/267/916949016/184007/38d1b676/5a43046aNef58b5a4.jpg","Name":"石末（SHIMO）休闲鞋","Introduce":"生活一天天继续，生活圈住的是我们的视野和脚步，圈不住的是对自由无限渴望—— ——石末（SHIMO）休闲鞋","OldPrice":658.0000,"CouponMoney":490.0000,"CommissionRate":0.200,"ShopTypeId":8,"PeiSongType":"京东","InsertTime":"2017-12-27T15:55:41.79","url":"https://union-click.jd.com/jdc?d=KiPMBG","uid":"1000000078","pid":"1113721487","shopid":22194,"shijiancha":169},{"Id":22195,"ImgUrl":"http://img14.360buyimg.com/imgzone/jfs/t7645/347/535690954/554809/54309b9a/5994162bN4d2225c2.jpg","Name":"大容量四件套学生书包 加厚帆布 精美卡通印花 ","Introduce":"大容量四件套学生书包 加厚帆布 精美卡通印花 原价69.9 领券下单立减30  券后价 39.9 另送精美小兔子毛绒挂件 超值低价 欲购从速哦！！！","OldPrice":69.9000,"CouponMoney":30.0000,"CommissionRate":0.300,"ShopTypeId":8,"PeiSongType":"京东","InsertTime":"2017-12-27T15:55:41.79","url":"https://union-click.jd.com/jdc?d=Y8N4RI","uid":"1000000078","pid":"1113721487","shopid":22195,"shijiancha":169},{"Id":22196,"ImgUrl":"http://img14.360buyimg.com/imgzone/jfs/t12415/61/527010488/568909/70659f25/5a0d6183N815ea5dd.jpg","Name":"莱诗伯特单肩包女新款女包","Introduce":"爆款来袭 韩版时尚单肩包 手提斜挎都是美美哒 送女友 送爱人 送老婆首选 满满的女神范儿  限时价59.9  含运费险 支持七天无理由退换货 让您购物无忧","OldPrice":69.9000,"CouponMoney":10.0000,"CommissionRate":0.200,"ShopTypeId":8,"PeiSongType":"京东","InsertTime":"2017-12-27T15:55:41.79","url":"https://union-click.jd.com/jdc?d=b8ZwPp","uid":"1000000078","pid":"1113721487","shopid":22196,"shijiancha":169},{"Id":22178,"ImgUrl":"http://img14.360buyimg.com/imgzone/jfs/t11581/29/2076741321/159480/e5139612/5a0fe6e7N4c21f985.jpg","Name":" 凯撒大帝真皮男士钱包商务休闲头层牛皮钱夹包","Introduce":"商领本色，甄选钱包，时尚儒雅，意式格调，精选优质牛皮，用心做真皮","OldPrice":149.0000,"CouponMoney":30.0000,"CommissionRate":0.200,"ShopTypeId":8,"PeiSongType":"京东","InsertTime":"2017-12-27T15:55:41.787","url":"https://union-click.jd.com/jdc?d=3i3WfQ","uid":"1000000078","pid":"1113721487","shopid":22178,"shijiancha":169},{"Id":22179,"ImgUrl":"http://img14.360buyimg.com/imgzone/jfs/t12631/42/640330652/129212/37a419da/5a0feb4fN978c0060.jpg","Name":" 凯撒大帝头层牛皮男士手包钱包","Introduce":"头层牛皮 大容量 多功能 商务休闲 精品男士手拿包 银行信用卡包 拉链开口","OldPrice":189.9000,"CouponMoney":50.0000,"CommissionRate":0.200,"ShopTypeId":8,"PeiSongType":"京东","InsertTime":"2017-12-27T15:55:41.787","url":"https://union-click.jd.com/jdc?d=ILD03H","uid":"1000000078","pid":"1113721487","shopid":22179,"shijiancha":169},{"Id":22181,"ImgUrl":"http://img14.360buyimg.com/imgzone/jfs/t16459/269/666617841/391811/b35ba36/5a3a1c53Nf1cc1615.jpg","Name":" 鸿星尔克（ERKE）运动鞋男款2018新品上市休闲鞋潮流","Introduce":"品牌直营，满199减20.潮流休闲鞋，怎么搭怎么火。舒适自在。","OldPrice":159.0000,"CouponMoney":30.0000,"CommissionRate":0.200,"ShopTypeId":8,"PeiSongType":"京东","InsertTime":"2017-12-27T15:55:41.787","url":"https://union-click.jd.com/jdc?d=jDoILd","uid":"1000000078","pid":"1113721487","shopid":22181,"shijiancha":169},{"Id":22182,"ImgUrl":"http://img.jingtuitui.com/23342201712271109268194.jpg","Name":"Hunkoo中学生书包女新款韩版波点猫印花双肩包小学生书包","Introduce":"领券直降10，赠送运费险，支持7天无理由退换！品牌书包，质量保证！","OldPrice":59.0000,"CouponMoney":10.0000,"CommissionRate":0.300,"ShopTypeId":8,"PeiSongType":"京东","InsertTime":"2017-12-27T15:55:41.787","url":"https://union-click.jd.com/jdc?d=5qfswf","uid":"1000000078","pid":"1113721487","shopid":22182,"shijiancha":169},{"Id":22183,"ImgUrl":"http://img14.360buyimg.com/imgzone/jfs/t3988/209/1292578725/102658/b9747ba/587265c6N13c57ded.jpg","Name":"秋冬大容量双肩包男女通用电脑包多功能学生书包","Introduce":"大容量学生书包 加厚帆布 精致做工可放15寸笔记本电脑 原价69.9 领券下单立减20  券后价 49.9  超值低价 欲购从速哦！！！","OldPrice":69.9000,"CouponMoney":20.0000,"CommissionRate":0.200,"ShopTypeId":8,"PeiSongType":"京东","InsertTime":"2017-12-27T15:55:41.787","url":"https://union-click.jd.com/jdc?d=5JKi5m","uid":"1000000078","pid":"1113721487","shopid":22183,"shijiancha":169},{"Id":22184,"ImgUrl":"http://img14.360buyimg.com/imgzone/jfs/t15268/66/858431754/94013/2adfa256/5a3bbf86N60f2a806.jpg","Name":"韩版包包女包新款印花单肩包气质百搭斜挎女式包","Introduce":"新款印花女包 新品上架 下单立减60 支持货到付款还送运费险","OldPrice":149.0000,"CouponMoney":60.0000,"CommissionRate":0.200,"ShopTypeId":8,"PeiSongType":"京东","InsertTime":"2017-12-27T15:55:41.787","url":"https://union-click.jd.com/jdc?d=7rOwun","uid":"1000000078","pid":"1113721487","shopid":22184,"shijiancha":169},{"Id":22186,"ImgUrl":"http://img14.360buyimg.com/imgzone/jfs/t15100/120/900091300/364487/f0416c5b/5a3bb68bN16386bb7.jpg","Name":"冬季新款女包韩版时尚印花单肩包气质百搭斜挎包","Introduce":"新品上架 限时优惠 现在下单立减80 支持货到付款 还送运费险","OldPrice":169.0000,"CouponMoney":80.0000,"CommissionRate":0.200,"ShopTypeId":8,"PeiSongType":"京东","InsertTime":"2017-12-27T15:55:41.787","url":"https://union-click.jd.com/jdc?d=9itn0z","uid":"1000000078","pid":"1113721487","shopid":22186,"shijiancha":169},{"Id":22187,"ImgUrl":"http://img14.360buyimg.com/imgzone/jfs/t15979/100/397782423/544649/43db7250/5a2fcb14Nc9cf827b.jpg","Name":"大容量四件套学生书包 加厚帆布 精美卡通印花 ","Introduce":"大容量四件套学生书包 加厚帆布 精美卡通印花 原价59.9 领券下单立减30  券后价 39.9 另送精美小熊毛绒挂件 超值低价 欲购从速哦！！！","OldPrice":59.9000,"CouponMoney":20.0000,"CommissionRate":0.200,"ShopTypeId":8,"PeiSongType":"京东","InsertTime":"2017-12-27T15:55:41.787","url":"https://union-click.jd.com/jdc?d=vblftR","uid":"1000000078","pid":"1113721487","shopid":22187,"shijiancha":169},{"Id":22188,"ImgUrl":"http://img14.360buyimg.com/imgzone/jfs/t5860/138/2607109701/503909/ee93ffa7/59325466Nc176d88c.jpg","Name":"长款男士钱包多卡位钱夹大容量零钱包","Introduce":"新款钱包长款多卡位钱夹 现在下单立减60 支持货到付款 还送运费险","OldPrice":99.0000,"CouponMoney":60.0000,"CommissionRate":0.300,"ShopTypeId":8,"PeiSongType":"京东","InsertTime":"2017-12-27T15:55:41.787","url":"https://union-click.jd.com/jdc?d=90A8iy","uid":"1000000078","pid":"1113721487","shopid":22188,"shijiancha":169},{"Id":22189,"ImgUrl":"http://img14.360buyimg.com/imgzone/jfs/t15373/177/858523424/445544/c8310bd1/5a3bb945N86fd77bf.jpg","Name":"印花女包韩版时尚单肩包休闲百搭斜挎包包","Introduce":"冬季新款女包 下单立减80 支持货到付款还送运费险 气质百搭包包 先买先得","OldPrice":169.0000,"CouponMoney":80.0000,"CommissionRate":0.200,"ShopTypeId":8,"PeiSongType":"京东","InsertTime":"2017-12-27T15:55:41.787","url":"https://union-click.jd.com/jdc?d=pgdIG7","uid":"1000000078","pid":"1113721487","shopid":22189,"shijiancha":169},{"Id":22191,"ImgUrl":"http://img14.360buyimg.com/imgzone/jfs/t7210/179/545640606/531370/d195e486/59944fb6N4cdde866.jpg","Name":"新款大容量学院风书包男女通用加厚帆布送挂件","Introduce":"秋冬大容量学生书包  加厚帆布 时尚撞色设计 精美卡通印花 原价69  领券下单立减30 券后价 39 另送精美卡通挂件 超值低价 限时抢购中！","OldPrice":69.0000,"CouponMoney":30.0000,"CommissionRate":0.200,"ShopTypeId":8,"PeiSongType":"京东","InsertTime":"2017-12-27T15:55:41.787","url":"https://union-click.jd.com/jdc?d=P8EN66","uid":"1000000078","pid":"1113721487","shopid":22191,"shijiancha":169},{"Id":22192,"ImgUrl":"http://img14.360buyimg.com/imgzone/jfs/t14467/150/583268462/212709/fb094f9a/5a3222f4N5e476a09.jpg","Name":"莱诗伯特女包复古老花女士手提包","Introduce":"经典复古老花手提包 斜挎手提都是美美哒 原价139 券后价99 送精美卡包 含运费险 支持七天无理由退换货  让您购物无忧 。预购速从","OldPrice":139.0000,"CouponMoney":40.0000,"CommissionRate":0.200,"ShopTypeId":8,"PeiSongType":"京东","InsertTime":"2017-12-27T15:55:41.787","url":"https://union-click.jd.com/jdc?d=0RKqbw","uid":"1000000078","pid":"1113721487","shopid":22192,"shijiancha":169},{"Id":22175,"ImgUrl":"http://img14.360buyimg.com/imgzone/jfs/t13708/8/623730999/250351/f7e5b84e/5a0fe6f0N1a92af1a.jpg","Name":"凯撒大帝商务休闲真皮短款男士钱包","Introduce":"商领本色，甄选钱包，时尚儒雅，意式格调，精选优质牛皮，用心做真皮","OldPrice":109.0000,"CouponMoney":20.0000,"CommissionRate":0.200,"ShopTypeId":8,"PeiSongType":"京东","InsertTime":"2017-12-27T15:55:41.76","url":"https://union-click.jd.com/jdc?d=qrHw5d","uid":"1000000078","pid":"1113721487","shopid":22175,"shijiancha":169},{"Id":22176,"ImgUrl":"http://img14.360buyimg.com/imgzone/jfs/t15940/68/897513344/467275/816debd0/5a41e6b2Ne6526067.jpg","Name":"韩版铆钉双肩包旅游休闲背包","Introduce":"2017新款女士双肩包韩版时尚铆钉背包旅游休闲包包妈咪包，原价99，券后79！","OldPrice":99.0000,"CouponMoney":20.0000,"CommissionRate":0.200,"ShopTypeId":8,"PeiSongType":"京东","InsertTime":"2017-12-27T15:55:41.76","url":"https://union-click.jd.com/jdc?d=OdLwj9","uid":"1000000078","pid":"1113721487","shopid":22176,"shijiancha":169},{"Id":22177,"ImgUrl":"http://img14.360buyimg.com/imgzone/jfs/t6649/345/694603778/239775/8fc924ee/5943a637Nc70b4040.jpg","Name":"羊皮菱格流苏迷你小钱包","Introduce":"【京东品质 亏本冲量】进口山羊皮，质感柔软，尽致菱格搭配流苏，美观小巧又不失使用性\n","OldPrice":118.0000,"CouponMoney":40.0000,"CommissionRate":0.200,"ShopTypeId":8,"PeiSongType":"京东","InsertTime":"2017-12-27T15:55:41.76","url":"https://union-click.jd.com/jdc?d=klN6QK","uid":"1000000078","pid":"1113721487","shopid":22177,"shijiancha":169},{"Id":22159,"ImgUrl":"http://img14.360buyimg.com/imgzone/jfs/t13876/243/586811416/80419/97bb7660/5a0ee707N38ded8f3.jpg","Name":"粉金刀叉勺3件套","Introduce":"树镇（SHUZHEN） 欧式粉金牛排刀叉套装家用刀叉勺玫瑰金不锈钢西餐高档餐具单品/套装 粉金刀叉勺3件套","OldPrice":109.0000,"CouponMoney":60.0000,"CommissionRate":0.250,"ShopTypeId":7,"PeiSongType":"京东","InsertTime":"2017-12-27T15:55:40.913","url":"https://union-click.jd.com/jdc?d=U8JELb","uid":"1000000078","pid":"1113721487","shopid":22159,"shijiancha":169},{"Id":22161,"ImgUrl":"http://img14.360buyimg.com/imgzone/jfs/t15412/263/1040390124/294223/24f83e4/5a43100eNf4315836.jpg","Name":" 桌面收纳篮塑料镂空收纳筐厨房零食收纳盒浴室洗澡篮","Introduce":"美观外形，结实耐用，仿藤编手提设计，更加时尚","OldPrice":13.9000,"CouponMoney":4.0000,"CommissionRate":0.200,"ShopTypeId":7,"PeiSongType":"京东","InsertTime":"2017-12-27T15:55:40.913","url":"https://union-click.jd.com/jdc?d=DO3UBv","uid":"1000000078","pid":"1113721487","shopid":22161,"shijiancha":169},{"Id":22164,"ImgUrl":"http://img14.360buyimg.com/imgzone/jfs/t14248/120/1012302759/666627/a2dd37d9/5a412591N7da89478.jpg","Name":"围裙  加绒加厚冬长袖款成人男女罩衣","Introduce":" 加绒加厚冬长袖款成人女围裙 带帽扣子正穿衣防水防污围裙","OldPrice":39.0000,"CouponMoney":10.0000,"CommissionRate":0.200,"ShopTypeId":7,"PeiSongType":"京东","InsertTime":"2017-12-27T15:55:40.913","url":"https://union-click.jd.com/jdc?d=EqBqRc","uid":"1000000078","pid":"1113721487","shopid":22164,"shijiancha":169},{"Id":22146,"ImgUrl":"http://img14.360buyimg.com/imgzone/jfs/t6016/256/4292480933/430919/36fa6a0e/5961ae1bN7c2a7564.jpg","Name":"禾艾苏（heisou）耐热玻璃水杯户外杯子带提绳送杯套","Introduce":"非常cool的一款杯子，颜值和逼格都爆表！","OldPrice":29.9000,"CouponMoney":10.0000,"CommissionRate":0.200,"ShopTypeId":7,"PeiSongType":"京东","InsertTime":"2017-12-27T15:55:40.903","url":"https://union-click.jd.com/jdc?d=f2OZXf","uid":"1000000078","pid":"1113721487","shopid":22146,"shijiancha":169},{"Id":22130,"ImgUrl":"http://img14.360buyimg.com/imgzone/jfs/t16042/19/867498595/735283/72a8dd08/5a409528N7d39b717.jpg","Name":"北欧风棉麻布艺围裙","Introduce":"树镇（SHUZHEN） 北欧风棉麻布艺围裙厨房防水可爱做饭女围腰防油男女工作服 黄色smile","OldPrice":26.0000,"CouponMoney":10.0000,"CommissionRate":0.200,"ShopTypeId":7,"PeiSongType":"京东","InsertTime":"2017-12-27T15:55:40.897","url":"https://union-click.jd.com/jdc?d=cfxhx8","uid":"1000000078","pid":"1113721487","shopid":22130,"shijiancha":169},{"Id":22131,"ImgUrl":"http://img14.360buyimg.com/imgzone/jfs/t14881/315/839838535/219045/3103020f/5a3b57d9Nd5194656.jpg","Name":"【暖暖暖100片活动限时秒杀】【无惧寒冬 温暖舒适】","Introduce":"2-3分钟即热，稳定发热53度，长达10小时发热。","OldPrice":48.0000,"CouponMoney":5.0000,"CommissionRate":0.200,"ShopTypeId":7,"PeiSongType":"京东","InsertTime":"2017-12-27T15:55:40.897","url":"https://union-click.jd.com/jdc?d=4cCRTc","uid":"1000000078","pid":"1113721487","shopid":22131,"shijiancha":169},{"Id":22134,"ImgUrl":"http://img14.360buyimg.com/imgzone/jfs/t13579/20/793411555/232688/c379db5f/5a13a3b4N0509f11c.jpg","Name":"金泰康 正品老北京足贴艾","Introduce":"睡眠差，易疲劳 贴一贴！外敷8小时， 晚上敷 早上撕 养足精神气！！！","OldPrice":29.9000,"CouponMoney":10.0000,"CommissionRate":0.200,"ShopTypeId":7,"PeiSongType":"京东","InsertTime":"2017-12-27T15:55:40.897","url":"https://union-click.jd.com/jdc?d=6k65zu","uid":"1000000078","pid":"1113721487","shopid":22134,"shijiancha":169},{"Id":22119,"ImgUrl":"http://img.jingtuitui.com/50cd5201712271104282302.jpg","Name":"新年拉花 彩带 吊旗 4个装","Introduce":"元旦拉花彩带装饰新年装饰品新春节庆用品彩条商场开业布置用品超市商店装饰 幼儿园活动 狗年吊旗 商店 公司年会 饭店装饰 教室学校晚会布置","OldPrice":39.0000,"CouponMoney":13.0000,"CommissionRate":0.200,"ShopTypeId":7,"PeiSongType":"京东","InsertTime":"2017-12-27T15:55:40.893","url":"https://union-click.jd.com/jdc?d=M4Jl15","uid":"1000000078","pid":"1113721487","shopid":22119,"shijiancha":169},{"Id":22121,"ImgUrl":"http://img14.360buyimg.com/imgzone/jfs/t16363/358/307288978/252545/542ee5fd/5a2df36dN5c670496.jpg","Name":"围裙 双肩无袖防水围裙 ","Introduce":"厨房双肩无袖防水围裙，防水防污，简约大方，材质优良，做工精细，轻盈耐脏！","OldPrice":39.0000,"CouponMoney":22.0000,"CommissionRate":0.200,"ShopTypeId":7,"PeiSongType":"京东","InsertTime":"2017-12-27T15:55:40.893","url":"https://union-click.jd.com/jdc?d=dvQIM0","uid":"1000000078","pid":"1113721487","shopid":22121,"shijiancha":169},{"Id":22122,"ImgUrl":"http://img.jingtuitui.com/3964820171227111037990.jpg","Name":"暖冬舒肤 冬被 羽丝绒填充","Introduce":"暖冬舒服被加厚保暖单双人冬被宾馆酒店磨毛被芯四季春秋床上用品空调被 亲肤面料 贴心背角扣设计 包边工艺","OldPrice":106.0000,"CouponMoney":27.0000,"CommissionRate":0.200,"ShopTypeId":7,"PeiSongType":"京东","InsertTime":"2017-12-27T15:55:40.893","url":"https://union-click.jd.com/jdc?d=w9bf4n","uid":"1000000078","pid":"1113721487","shopid":22122,"shijiancha":169},{"Id":22124,"ImgUrl":"http://img.jingtuitui.com/46486201712271513091656.jpg","Name":"中国结挂件福字装饰品","Introduce":"无纺布大红中国结挂件过年春节福字毛毡布装饰用品，恭贺新春，美满团圆。","OldPrice":56.0000,"CouponMoney":14.0000,"CommissionRate":0.200,"ShopTypeId":7,"PeiSongType":"京东","InsertTime":"2017-12-27T15:55:40.893","url":"https://union-click.jd.com/jdc?d=F0laUF","uid":"1000000078","pid":"1113721487","shopid":22124,"shijiancha":169},{"Id":22128,"ImgUrl":"http://img14.360buyimg.com/imgzone/jfs/t1999/44/1938698007/282947/6c229efd/56e77e71N2388afcd.jpg","Name":"自油自画 数字油画diy手绘油画填色画","Introduce":"数字油画，纯手绘油画，让你一分钟画出大师作品\n","OldPrice":79.0000,"CouponMoney":40.0000,"CommissionRate":0.300,"ShopTypeId":7,"PeiSongType":"京东","InsertTime":"2017-12-27T15:55:40.893","url":"https://union-click.jd.com/jdc?d=vvqXqB","uid":"1000000078","pid":"1113721487","shopid":22128,"shijiancha":169},{"Id":22092,"ImgUrl":"http://img14.360buyimg.com/imgzone/jfs/t15331/188/659058772/299758/42c496dd/5a34750dN60cd1e3b.jpg","Name":"湖南特产红烧肉 真空包装200g 开袋加热即食","Introduce":"领10优惠券！买2送1！红烧肉200g！加热即食！方便食品！","OldPrice":29.8000,"CouponMoney":10.0000,"CommissionRate":0.200,"ShopTypeId":6,"PeiSongType":"京东","InsertTime":"2017-12-27T15:55:38.83","url":"https://union-click.jd.com/jdc?d=TrKypj","uid":"1000000078","pid":"1113721487","shopid":22092,"shijiancha":169},{"Id":22071,"ImgUrl":"http://img.jingtuitui.com/80b81201712271522342469.jpg","Name":"【大牌来袭】前进牌 桃酥糕点小吃 2000g","Introduce":"湖南名牌，三十年特产老字号，鲜香酥脆，入口即化，吃过的都说好，早餐下午茶的必备佳品！","OldPrice":49.9000,"CouponMoney":10.0000,"CommissionRate":0.200,"ShopTypeId":6,"PeiSongType":"京东","InsertTime":"2017-12-27T15:55:38.817","url":"https://union-click.jd.com/jdc?d=Pr9xdF","uid":"1000000078","pid":"1113721487","shopid":22071,"shijiancha":169},{"Id":22077,"ImgUrl":"http://img.jingtuitui.com/1b904201712271516127324.jpg","Name":"【5斤装】丑橘不知火","Introduce":"别看我丑，但我很好吃！产地直供，新鲜采摘，果肉细嫩，吃上一口永难忘！","OldPrice":49.9000,"CouponMoney":15.0000,"CommissionRate":0.200,"ShopTypeId":6,"PeiSongType":"京东","InsertTime":"2017-12-27T15:55:38.817","url":"https://union-click.jd.com/jdc?d=ldwRbA","uid":"1000000078","pid":"1113721487","shopid":22077,"shijiancha":169},{"Id":22047,"ImgUrl":"http://img14.360buyimg.com/imgzone/jfs/t13420/168/259539972/177052/7916fe97/5a0736d5N51c16fd2.jpg","Name":"透真玻尿酸多效保湿蚕丝眼膜贴20片","Introduce":"下单即送多3片，顾客都选这款！ 每天一片，敷出水润亮采。","OldPrice":69.0000,"CouponMoney":20.0000,"CommissionRate":0.200,"ShopTypeId":5,"PeiSongType":"京东","InsertTime":"2017-12-27T15:55:37.687","url":"https://union-click.jd.com/jdc?d=pSHikc","uid":"1000000078","pid":"1113721487","shopid":22047,"shijiancha":169},{"Id":22048,"ImgUrl":"http://img14.360buyimg.com/imgzone/jfs/t6112/322/4068891386/280238/192429de/595efc0dNabe25f83.jpg","Name":"透真玻尿酸洗面奶120g","Introduce":"买一送一，明星同款推荐！ 温和洁面，洁净不紧绷！","OldPrice":59.0000,"CouponMoney":20.0000,"CommissionRate":0.250,"ShopTypeId":5,"PeiSongType":"京东","InsertTime":"2017-12-27T15:55:37.687","url":"https://union-click.jd.com/jdc?d=q08jtp","uid":"1000000078","pid":"1113721487","shopid":22048,"shijiancha":169},{"Id":22049,"ImgUrl":"http://img14.360buyimg.com/imgzone/jfs/t12421/3/927781456/151411/8fe75dfc/5a167cf1N093627f0.jpg","Name":" 透真修容遮瑕笔","Introduce":"一笔遮瑕 自然美肌 券后29包邮!买就是保湿面膜1片！","OldPrice":49.0000,"CouponMoney":20.0000,"CommissionRate":0.300,"ShopTypeId":5,"PeiSongType":"京东","InsertTime":"2017-12-27T15:55:37.687","url":"https://union-click.jd.com/jdc?d=EFI9QH","uid":"1000000078","pid":"1113721487","shopid":22049,"shijiancha":169},{"Id":22006,"ImgUrl":"http://img14.360buyimg.com/imgzone/jfs/t16531/138/791452268/190507/13a369ea/5a40bec2N8fa1e41f.jpg","Name":"欧美超大围巾女仿羊绒纯色保暖围脖披肩两用加厚围巾","Introduce":"纯色保暖围脖披肩两用加厚围巾，精选仿羊绒，放心与脸部皮肤亲密接触\n","OldPrice":69.0000,"CouponMoney":30.0000,"CommissionRate":0.300,"ShopTypeId":3,"PeiSongType":"京东","InsertTime":"2017-12-27T15:55:37.047","url":"https://union-click.jd.com/jdc?d=6AL3Bq","uid":"1000000078","pid":"1113721487","shopid":22006,"shijiancha":169},{"Id":22009,"ImgUrl":"http://img14.360buyimg.com/imgzone/jfs/t12439/97/2403049753/391142/a1860f91/5a3be11bN546383b8.jpg","Name":"珂珂熙妮毛线帽子女冬韩版潮流学生针织套头帽","Introduce":"精选毛线编织，柔软舒适，里层加绒保暖，下单仅需29！","OldPrice":49.0000,"CouponMoney":20.0000,"CommissionRate":0.200,"ShopTypeId":3,"PeiSongType":"京东","InsertTime":"2017-12-27T15:55:37.047","url":"https://union-click.jd.com/jdc?d=KObAw4","uid":"1000000078","pid":"1113721487","shopid":22009,"shijiancha":169},{"Id":22010,"ImgUrl":"http://img14.360buyimg.com/imgzone/jfs/t16567/104/826915963/361430/af07059b/5a40c501N93b176c0.jpg","Name":"韩版仿羊绒围巾女长款纯色保暖围脖加厚百搭原宿披肩","Introduce":"纯色百搭保暖围脖披肩，精选柔软仿羊绒，放心与脸部皮肤亲密接触\n","OldPrice":79.0000,"CouponMoney":30.0000,"CommissionRate":0.200,"ShopTypeId":3,"PeiSongType":"京东","InsertTime":"2017-12-27T15:55:37.047","url":"https://union-click.jd.com/jdc?d=f7fESy","uid":"1000000078","pid":"1113721487","shopid":22010,"shijiancha":169},{"Id":22012,"ImgUrl":"http://img14.360buyimg.com/imgzone/jfs/t16156/141/178339261/469545/9177ed63/5a2a0500Nb022edd5.jpg","Name":"秋冬法兰绒珊瑚绒女睡衣套装可爱韩版加厚家居服","Introduce":"优选法兰绒面料，高密细腻，亲肤舒适又保暖，韩版时尚造型，冬季必备一套~","OldPrice":49.0000,"CouponMoney":10.0000,"CommissionRate":0.200,"ShopTypeId":3,"PeiSongType":"京东","InsertTime":"2017-12-27T15:55:37.047","url":"https://union-click.jd.com/jdc?d=wAUYiA","uid":"1000000078","pid":"1113721487","shopid":22012,"shijiancha":169},{"Id":21976,"ImgUrl":"http://img14.360buyimg.com/imgzone/jfs/t14626/248/1042468469/339224/a51cdf95/5a430cc3N00f1c54d.jpg","Name":"石末（SHIMO）冬季新款中长款修身潮男毛呢大衣","Introduce":"生活一天天继续，生活圈住的是我们的视野和脚步，圈不住的是对自由无限渴望—— ——石末（SHIMO）毛呢大衣","OldPrice":712.0000,"CouponMoney":410.0000,"CommissionRate":0.200,"ShopTypeId":2,"PeiSongType":"京东","InsertTime":"2017-12-27T15:55:36.963","url":"https://union-click.jd.com/jdc?d=kx8Hjg","uid":"1000000078","pid":"1113721487","shopid":21976,"shijiancha":169},{"Id":21977,"ImgUrl":"http://img14.360buyimg.com/imgzone/jfs/t14200/364/1053709899/443604/e85487ca/5a430d3aN1629dbe7.jpg","Name":"石末（SHIMO）毛呢大衣","Introduce":"生活一天天继续，生活圈住的是我们的视野和脚步，圈不住的是对自由无限渴望—— ——石末（SHIMO）毛呢大衣","OldPrice":735.0000,"CouponMoney":470.0000,"CommissionRate":0.200,"ShopTypeId":2,"PeiSongType":"京东","InsertTime":"2017-12-27T15:55:36.963","url":"https://union-click.jd.com/jdc?d=1nW7ZY","uid":"1000000078","pid":"1113721487","shopid":21977,"shijiancha":169},{"Id":21978,"ImgUrl":"http://img14.360buyimg.com/imgzone/jfs/t16024/135/917566266/98948/1742dd78/5a42fef9Nfe977467.jpg","Name":"【富贵鸟 品牌直销】2017新款马甲男修身时尚保暖背心","Introduce":"多色可选，时尚潮流，帅气百搭，保暖有型！今天特价，限量抢购！","OldPrice":198.0000,"CouponMoney":100.0000,"CommissionRate":0.250,"ShopTypeId":2,"PeiSongType":"京东","InsertTime":"2017-12-27T15:55:36.963","url":"https://union-click.jd.com/jdc?d=dUSL5K","uid":"1000000078","pid":"1113721487","shopid":21978,"shijiancha":169},{"Id":21982,"ImgUrl":"http://img14.360buyimg.com/imgzone/jfs/t2479/224/550961252/492380/ae9bdda2/5615559eN1a669d31.jpg","Name":"韩版加绒加厚休闲修身商务衬衣","Introduce":"加厚蓄热钻石绒，蓄热复合一体，360°全面呵护，对抗零下20℃严寒，冬日必备之选~~~","OldPrice":128.0000,"CouponMoney":69.0000,"CommissionRate":0.200,"ShopTypeId":2,"PeiSongType":"京东","InsertTime":"2017-12-27T15:55:36.963","url":"https://union-click.jd.com/jdc?d=IKvoiF","uid":"1000000078","pid":"1113721487","shopid":21982,"shijiancha":169},{"Id":21997,"ImgUrl":"http://img14.360buyimg.com/imgzone/jfs/t11947/148/319399126/185686/42af459/59ec9707N19e9c202.jpg","Name":"婴儿袜秋冬毛圈加厚中筒儿童宝宝袜子纯棉 ","Introduce":"冬款加厚宝宝袜，除延续以往的仿手工对目和柔软材质外，还根据婴儿脚型和活动特点，对袜子的罗口和后跟做了细节优化，真正起到“即保保暖不勒又不掉 \n","OldPrice":38.0000,"CouponMoney":10.0000,"CommissionRate":0.200,"ShopTypeId":4,"PeiSongType":"京东","InsertTime":"2017-12-27T15:55:36.933","url":"https://union-click.jd.com/jdc?d=RFDKtk","uid":"1000000078","pid":"1113721487","shopid":21997,"shijiancha":169},{"Id":22001,"ImgUrl":"http://img14.360buyimg.com/imgzone/jfs/t13426/67/726809235/108850/743aa995/5a1276faNbf3c11ba.jpg","Name":"婴儿卡通连体衣婴童冬款卡通加绒连体衣 ","Introduce":"小恐龙婴儿连体衣然你的宝宝到哪都是一道风景 \n","OldPrice":199.0000,"CouponMoney":40.0000,"CommissionRate":0.200,"ShopTypeId":4,"PeiSongType":"京东","InsertTime":"2017-12-27T15:55:36.933","url":"https://union-click.jd.com/jdc?d=TN3gM2","uid":"1000000078","pid":"1113721487","shopid":22001,"shijiancha":169},{"Id":22005,"ImgUrl":"http://img.jingtuitui.com/3abd2201712271132379642.jpg","Name":"【送运费险】吉米尤克里里小吉他 M-16（23寸）","Introduce":"手感舒适，拉弦不费力，24小时易上手，专业教学，终生售后！","OldPrice":199.0000,"CouponMoney":30.0000,"CommissionRate":0.200,"ShopTypeId":4,"PeiSongType":"京东","InsertTime":"2017-12-27T15:55:36.933","url":"https://union-click.jd.com/jdc?d=gY2cEa","uid":"1000000078","pid":"1113721487","shopid":22005,"shijiancha":169},{"Id":21975,"ImgUrl":"http://img.jingtuitui.com/3c8d3201712271236481116.jpg","Name":"【富贵鸟 品牌直销】2017新款马甲男修身时尚保暖背心","Introduce":"【年末品牌清仓钜惠】【修身潮搭】多色可选，时尚潮流，帅气百搭，保暖有型！今天特价，限量抢购！","OldPrice":238.0000,"CouponMoney":120.0000,"CommissionRate":0.250,"ShopTypeId":2,"PeiSongType":"京东","InsertTime":"2017-12-27T15:55:36.933","url":"https://union-click.jd.com/jdc?d=44JVKr","uid":"1000000078","pid":"1113721487","shopid":21975,"shijiancha":169},{"Id":21983,"ImgUrl":"http://img14.360buyimg.com/imgzone/jfs/t11065/218/362845919/215986/c7719942/59eea9e3Nb963a24f.png","Name":"兼容乐高塑料儿童积木桌小颗粒","Introduce":"送200颗粒积木！兼容乐高！多功能积木桌！底板 收纳 学习","OldPrice":69.0000,"CouponMoney":20.0000,"CommissionRate":0.200,"ShopTypeId":4,"PeiSongType":"京东","InsertTime":"2017-12-27T15:55:36.927","url":"https://union-click.jd.com/jdc?d=tdRS0M","uid":"1000000078","pid":"1113721487","shopid":21983,"shijiancha":169},{"Id":21985,"ImgUrl":"http://img.jingtuitui.com/6ff84201712271322494694.gif","Name":"儿童四轮滑板车双脚摇摆滑滑车毛毛虫蛙式车 ","Introduce":"儿童四轮滑板车四轮全刹系统安全平稳全新八大升级给宝贝更加安全的童年！ \n","OldPrice":399.0000,"CouponMoney":170.0000,"CommissionRate":0.200,"ShopTypeId":4,"PeiSongType":"京东","InsertTime":"2017-12-27T15:55:36.927","url":"https://union-click.jd.com/jdc?d=wh4IPc","uid":"1000000078","pid":"1113721487","shopid":21985,"shijiancha":169},{"Id":21988,"ImgUrl":"http://img14.360buyimg.com/imgzone/jfs/t14026/97/2170213346/287322/43335d11/5a349471N7fec9f3f.jpg","Name":"里奥船长xpe爬行垫双面加厚","Introduce":"全xpe材质，密度大弹性好，安全环保无异味，隔凉防潮，益智早教，送运费险售后无忧。\n","OldPrice":138.0000,"CouponMoney":50.0000,"CommissionRate":0.200,"ShopTypeId":4,"PeiSongType":"京东","InsertTime":"2017-12-27T15:55:36.927","url":"https://union-click.jd.com/jdc?d=P8pL6s","uid":"1000000078","pid":"1113721487","shopid":21988,"shijiancha":169},{"Id":21990,"ImgUrl":"http://img14.360buyimg.com/imgzone/jfs/t12871/72/1728879490/189146/e9104736/5a277568Ne8ff4156.jpg","Name":"宝宝牛仔罩衣纯棉婴儿吃饭衣男女童罩衣秋冬长袖围裙 ","Introduce":"纯棉牛仔罩衣，宝宝罩衣也可以很时尚，舒适柔软，亲肤透气。 \n","OldPrice":89.0000,"CouponMoney":40.0000,"CommissionRate":0.200,"ShopTypeId":4,"PeiSongType":"京东","InsertTime":"2017-12-27T15:55:36.927","url":"https://union-click.jd.com/jdc?d=4d6Bwe","uid":"1000000078","pid":"1113721487","shopid":21990,"shijiancha":169},{"Id":21991,"ImgUrl":"http://img14.360buyimg.com/imgzone/jfs/t11248/310/72369434/182574/f42a4550/59e705d1Na7dacaca.jpg","Name":"婴儿湿纸巾婴儿棉柔巾新生儿湿纸巾 ","Introduce":"皇家宝贝婴儿柔软湿巾80抽4包装一巾在手宝妈无忧 \n","OldPrice":39.9000,"CouponMoney":10.0000,"CommissionRate":0.200,"ShopTypeId":4,"PeiSongType":"京东","InsertTime":"2017-12-27T15:55:36.927","url":"https://union-click.jd.com/jdc?d=NsgBiS","uid":"1000000078","pid":"1113721487","shopid":21991,"shijiancha":169},{"Id":21995,"ImgUrl":"http://img14.360buyimg.com/imgzone/jfs/t9958/152/1641953628/168001/17976498/59e41e29N79931046.jpg","Name":"宝宝防摔头部保护垫学步防摔枕 ","Introduce":"宝宝防摔头部保护垫 宝宝学走路防摔防撞护头枕给宝宝一个安全的起步起步利器 \n","OldPrice":49.0000,"CouponMoney":10.0000,"CommissionRate":0.200,"ShopTypeId":4,"PeiSongType":"京东","InsertTime":"2017-12-27T15:55:36.927","url":"https://union-click.jd.com/jdc?d=bsECGd","uid":"1000000078","pid":"1113721487","shopid":21995,"shijiancha":169},{"Id":21965,"ImgUrl":"http://img14.360buyimg.com/imgzone/jfs/t10378/153/1467682564/413502/8046c86c/59e1aea0Neadc5147.jpg","Name":"中年女装冬装中长款羽绒棉服妈妈装","Introduce":"冬装中长款棉服女装 款式时尚年轻 质量保证 全国包邮","OldPrice":218.0000,"CouponMoney":40.0000,"CommissionRate":0.200,"ShopTypeId":1,"PeiSongType":"京东","InsertTime":"2017-12-27T15:55:36.8","url":"https://union-click.jd.com/jdc?d=Mb5rHp","uid":"1000000078","pid":"1113721487","shopid":21965,"shijiancha":169},{"Id":21967,"ImgUrl":"http://img14.360buyimg.com/imgzone/jfs/t10045/197/1537588437/466375/ae6f5412/59e2da5bN92e87526.jpg","Name":"中老年女装冬装棉服中长款妈妈装","Introduce":"时尚休闲中年女装羽绒棉服中长款妈妈装 质量保证 支持退换","OldPrice":188.0000,"CouponMoney":30.0000,"CommissionRate":0.200,"ShopTypeId":1,"PeiSongType":"京东","InsertTime":"2017-12-27T15:55:36.8","url":"https://union-click.jd.com/jdc?d=ZWxE9I","uid":"1000000078","pid":"1113721487","shopid":21967,"shijiancha":169},{"Id":21968,"ImgUrl":"http://img14.360buyimg.com/imgzone/jfs/t10819/104/947004273/501652/ef9499ca/59dae388N6f6bff7d.jpg","Name":"女装针织衫加厚加绒妈妈装","Introduce":"时尚妈妈装冬装保暖针织衫 加厚内里加绒 质量保证 支持推换","OldPrice":178.0000,"CouponMoney":30.0000,"CommissionRate":0.200,"ShopTypeId":1,"PeiSongType":"京东","InsertTime":"2017-12-27T15:55:36.8","url":"https://union-click.jd.com/jdc?d=bVEK8p","uid":"1000000078","pid":"1113721487","shopid":21968,"shijiancha":169},{"Id":21969,"ImgUrl":"http://img14.360buyimg.com/imgzone/jfs/t10243/209/999232091/387147/cab8d600/59dae8a1N06d9f283.jpg","Name":"女装针织衫加厚加绒羊毛衫妈妈装","Introduce":"时尚妈妈装冬装针织衫加厚加绒保暖 面料舒适 质量保证 支持退换","OldPrice":178.0000,"CouponMoney":30.0000,"CommissionRate":0.200,"ShopTypeId":1,"PeiSongType":"京东","InsertTime":"2017-12-27T15:55:36.8","url":"https://union-click.jd.com/jdc?d=8bHXYl","uid":"1000000078","pid":"1113721487","shopid":21969,"shijiancha":169},{"Id":21970,"ImgUrl":"http://img14.360buyimg.com/imgzone/jfs/t11065/292/134803283/416185/ec1a9d9d/59e86307N5d3827d9.jpg","Name":"中年女装冬装棉服保暖妈妈装","Introduce":"时尚妈妈装女装冬装羽绒棉服 保暖加厚 质量保证 支持退换","OldPrice":178.0000,"CouponMoney":30.0000,"CommissionRate":0.200,"ShopTypeId":1,"PeiSongType":"京东","InsertTime":"2017-12-27T15:55:36.8","url":"https://union-click.jd.com/jdc?d=I19wJp","uid":"1000000078","pid":"1113721487","shopid":21970,"shijiancha":169},{"Id":21971,"ImgUrl":"http://img14.360buyimg.com/imgzone/jfs/t10234/315/1595897229/334012/c7d3d86e/59e2df38Nc06775b1.jpg","Name":"朗臣中年女装羽绒棉服保暖妈妈装","Introduce":"年终大促冬装保暖羽绒棉服 质量保证 全国包邮 支持退换","OldPrice":188.0000,"CouponMoney":30.0000,"CommissionRate":0.200,"ShopTypeId":1,"PeiSongType":"京东","InsertTime":"2017-12-27T15:55:36.8","url":"https://union-click.jd.com/jdc?d=v88piW","uid":"1000000078","pid":"1113721487","shopid":21971,"shijiancha":169},{"Id":21972,"ImgUrl":"http://img14.360buyimg.com/imgzone/jfs/t12751/342/17646898/173534/3a555e28/5a01bd9aNa42d693b.jpg","Name":"2017秋冬新款半高领毛衣打底衫修身显瘦针织衫 ","Introduce":"修身打底衫，针织衫，多达8种颜色可以供亲选择。","OldPrice":69.0000,"CouponMoney":20.0000,"CommissionRate":0.200,"ShopTypeId":1,"PeiSongType":"京东","InsertTime":"2017-12-27T15:55:36.8","url":"https://union-click.jd.com/jdc?d=v2Z5Ny","uid":"1000000078","pid":"1113721487","shopid":21972,"shijiancha":169},{"Id":21962,"ImgUrl":"http://img14.360buyimg.com/imgzone/jfs/t9838/54/654868697/380786/5e0fb181/59d61e19N26749e06.jpg","Name":"中年女装针织衫中长款打底衫妈妈装","Introduce":"优质面料 质量保证 中年女装打底衫中长款 全国包邮 支持退换","OldPrice":178.0000,"CouponMoney":30.0000,"CommissionRate":0.200,"ShopTypeId":1,"PeiSongType":"京东","InsertTime":"2017-12-27T15:55:36.797","url":"https://union-click.jd.com/jdc?d=tTfe9A","uid":"1000000078","pid":"1113721487","shopid":21962,"shijiancha":169},{"Id":21963,"ImgUrl":"http://img14.360buyimg.com/imgzone/jfs/t9544/343/958974549/445690/935d851a/59daea41Ndc8b0266.jpg","Name":"中年女装针织衫加厚保暖加绒妈妈装","Introduce":"中年女装冬装加厚加绒针织衫 面料舒适 质量保证 全国包邮","OldPrice":178.0000,"CouponMoney":30.0000,"CommissionRate":0.200,"ShopTypeId":1,"PeiSongType":"京东","InsertTime":"2017-12-27T15:55:36.797","url":"https://union-click.jd.com/jdc?d=AZpgqw","uid":"1000000078","pid":"1113721487","shopid":21963,"shijiancha":169},{"Id":21901,"ImgUrl":"http://img.jingtuitui.com/1761b201712271046245463.jpg","Name":"儿童枕套 纯棉六层棉纱布","Introduce":"卡通幼儿园枕头芯套单个蓝色条纹棉纱布加大加厚可爱整头罩套 圣诞树蓝","OldPrice":39.0000,"CouponMoney":11.0000,"CommissionRate":0.200,"ShopTypeId":7,"PeiSongType":"京东","InsertTime":"2017-12-27T11:17:46.14","url":"https://union-click.jd.com/jdc?d=r8f9DH","uid":"1000000078","pid":"1113721487","shopid":21901,"shijiancha":173},{"Id":21894,"ImgUrl":"http://img14.360buyimg.com/imgzone/jfs/t11533/365/389621657/64434/434d92c2/59f00875Ne3501bb9.jpg","Name":"DHC纯橄榄润唇膏1.5g","Introduce":"你与干燥天气只差一只DHC，不仅触感自然、不粘腻，且具有优异的滋润力和保湿力，是迅速润泽粗糙双唇、打破唇部护理常识的人气护唇膏。\n\n","OldPrice":69.0000,"CouponMoney":20.0000,"CommissionRate":0.200,"ShopTypeId":5,"PeiSongType":"京东","InsertTime":"2017-12-27T11:17:45.447","url":"https://union-click.jd.com/jdc?d=crd3Ba","uid":"1000000078","pid":"1113721487","shopid":21894,"shijiancha":173},{"Id":21883,"ImgUrl":"http://img14.360buyimg.com/imgzone/jfs/t16120/230/858261240/417336/48fb5299/5a41fe05N2a7d727a.jpg","Name":"新款女士双肩包铆钉背包","Introduce":"2017新款女士双肩包韩版时尚印花铆钉休闲背包旅行包包，时尚百搭，经典必备，原价99，券后79！","OldPrice":99.0000,"CouponMoney":20.0000,"CommissionRate":0.200,"ShopTypeId":8,"PeiSongType":"京东","InsertTime":"2017-12-27T10:56:30.827","url":"https://union-click.jd.com/jdc?d=pN5Q9r","uid":"1000000078","pid":"1113721487","shopid":21883,"shijiancha":174},{"Id":21877,"ImgUrl":"http://img.jingtuitui.com/508ef201712271048169235.jpg","Name":"【京仓直发】时尚情侣纯色套头帽","Introduce":"【送运费险】美“帽”与实力并存，多色可选，舒适温暖，一帽多带，告别臃肿繁琐，让你瞬间又暖又有型！","OldPrice":36.0000,"CouponMoney":17.0000,"CommissionRate":0.300,"ShopTypeId":3,"PeiSongType":"京东配送","InsertTime":"2017-12-27T10:56:15.733","url":"https://union-click.jd.com/jdc?d=JCmPNI","uid":"1000000078","pid":"1113721487","shopid":21877,"shijiancha":174},{"Id":21826,"ImgUrl":"http://img14.360buyimg.com/imgzone/jfs/t13042/252/2319673572/299730/8723a33c/5a3a4d25Ncfa2fa16.jpg","Name":"小号桌面垃圾桶","Introduce":"小号桌面垃圾桶创意迷你办公桌按压圆形废纸篓垃圾筒带盖收纳桶 ","OldPrice":22.0000,"CouponMoney":5.0000,"CommissionRate":0.200,"ShopTypeId":7,"PeiSongType":"京东","InsertTime":"2017-12-27T10:44:38.973","url":"https://union-click.jd.com/jdc?d=UZ7kNy","uid":"1000000078","pid":"1113721487","shopid":21826,"shijiancha":174},{"Id":21822,"ImgUrl":"http://img.jingtuitui.com/76c30201712261113264038.jpg","Name":"【亏本冲量/柔软亲肤】浴巾 强吸水成人柔软亲肤浴巾","Introduce":"1件2套 优质选材 强吸水 柔软亲肤加厚款","OldPrice":49.0000,"CouponMoney":10.0000,"CommissionRate":0.200,"ShopTypeId":7,"PeiSongType":"京东","InsertTime":"2017-12-27T10:44:38.97","url":"https://union-click.jd.com/jdc?d=bzGAfl","uid":"1000000078","pid":"1113721487","shopid":21822,"shijiancha":174},{"Id":21814,"ImgUrl":"http://img14.360buyimg.com/imgzone/jfs/t15460/219/585114360/428711/1f6250cb/5a323c00Nf849730c.jpg","Name":"瓜子糖果盒 分格带盖干果盒 过年必备","Introduce":"早买早优惠 过年居家生活必备 产品上新有优惠 可分格带盖造型独特 放在家里好看又好用","OldPrice":39.9000,"CouponMoney":10.0000,"CommissionRate":0.200,"ShopTypeId":7,"PeiSongType":"京东","InsertTime":"2017-12-27T10:44:38.96","url":"https://union-click.jd.com/jdc?d=p2df0U","uid":"1000000078","pid":"1113721487","shopid":21814,"shijiancha":174},{"Id":21815,"ImgUrl":"http://img14.360buyimg.com/imgzone/jfs/t10102/308/1167627/116742/33910a3d/59c334ceNa00f102a.jpg","Name":" 保温杯 304不锈钢 保温杯子","Introduce":"多色可选，更懂你的水杯，你要健康和安全感，健康优选优质材料，耐磨杯底平滑杯口，默默相互，每天拥有小幸运！","OldPrice":49.9000,"CouponMoney":30.0000,"CommissionRate":0.300,"ShopTypeId":7,"PeiSongType":"京东","InsertTime":"2017-12-27T10:44:38.96","url":"https://union-click.jd.com/jdc?d=GHinZ1","uid":"1000000078","pid":"1113721487","shopid":21815,"shijiancha":174},{"Id":21810,"ImgUrl":"http://img.jingtuitui.com/04ad4201712261408147004.jpg","Name":"进口意大利沙芬电子烟大烟雾补充维他命辅助戒烟","Introduce":"进口电子烟强劲大烟雾即刻补充维他命可吸约600口","OldPrice":83.8000,"CouponMoney":20.0000,"CommissionRate":0.200,"ShopTypeId":7,"PeiSongType":"京东","InsertTime":"2017-12-27T10:44:38.957","url":"https://union-click.jd.com/jdc?d=h4y2IH","uid":"1000000078","pid":"1113721487","shopid":21810,"shijiancha":174},{"Id":21807,"ImgUrl":"http://img14.360buyimg.com/imgzone/jfs/t16318/347/795102756/471308/17bbb0ba/5a40e2bfN8ae8fef0.jpg","Name":"防滑环保筷子家用","Introduce":"树镇（SHUZHEN） 小麦桔秆防滑环保筷子家用日式大人儿童餐具创意环保防霉 4-30双 4双装","OldPrice":15.0000,"CouponMoney":5.0000,"CommissionRate":0.200,"ShopTypeId":7,"PeiSongType":"京东","InsertTime":"2017-12-27T10:44:38.953","url":"https://union-click.jd.com/jdc?d=9OM85M","uid":"1000000078","pid":"1113721487","shopid":21807,"shijiancha":174},{"Id":21786,"ImgUrl":"http://img14.360buyimg.com/imgzone/jfs/t4792/94/1545033137/391924/239f0723/58f1b1f1N7f5105eb.jpg","Name":"禾艾苏（heisou）耐热玻璃茶壶送4个茶杯","Introduce":"时尚泡茶壶，居家办公一壶多用。泡一壶好茶，为健康加分！","OldPrice":29.9000,"CouponMoney":10.0000,"CommissionRate":0.200,"ShopTypeId":7,"PeiSongType":"京东","InsertTime":"2017-12-27T10:44:38.917","url":"https://union-click.jd.com/jdc?d=Oc8TaA","uid":"1000000078","pid":"1113721487","shopid":21786,"shijiancha":174},{"Id":21784,"ImgUrl":"http://img14.360buyimg.com/imgzone/jfs/t12097/229/2500856946/373888/8f51f70b/5a420aa1N79975723.jpg","Name":"迷你榨汁机手动家用水果榨汁机器简易手动压汁器","Introduce":"优质选材 安全健康 操作简单易上手 一物俩用营养随时想用","OldPrice":29.9000,"CouponMoney":4.0000,"CommissionRate":0.200,"ShopTypeId":7,"PeiSongType":"京东","InsertTime":"2017-12-27T10:44:38.913","url":"https://union-click.jd.com/jdc?d=zvbvu5","uid":"1000000078","pid":"1113721487","shopid":21784,"shijiancha":174},{"Id":21775,"ImgUrl":"http://img14.360buyimg.com/imgzone/jfs/t12289/116/1906080988/323192/76846114/5a2d54c8N38d2f85c.jpg","Name":"时尚平底大码加绒加厚休闲皮鞋男","Introduce":"休闲时尚皮鞋男，内里加绒加厚保暖。鞋底采用橡胶大底，防滑。优质二层牛皮","OldPrice":159.0000,"CouponMoney":60.0000,"CommissionRate":0.200,"ShopTypeId":8,"PeiSongType":"京东","InsertTime":"2017-12-27T10:44:36.007","url":"https://union-click.jd.com/jdc?d=BfqbN5","uid":"1000000078","pid":"1113721487","shopid":21775,"shijiancha":174},{"Id":21774,"ImgUrl":"http://img14.360buyimg.com/imgzone/jfs/t13951/85/1866891850/206163/5893ac88/5a2bef54Nc6bde3a6.jpg","Name":"时尚平底大码加绒加厚休闲皮鞋男","Introduce":"休闲时尚皮鞋男，内里加绒加厚保暖。鞋底采用橡胶大底，防滑。优质二层牛皮","OldPrice":159.0000,"CouponMoney":60.0000,"CommissionRate":0.200,"ShopTypeId":8,"PeiSongType":"京东","InsertTime":"2017-12-27T10:44:35.997","url":"https://union-click.jd.com/jdc?d=roXPV2","uid":"1000000078","pid":"1113721487","shopid":21774,"shijiancha":174},{"Id":21772,"ImgUrl":"http://img14.360buyimg.com/imgzone/jfs/t10606/235/1240302047/438850/4849068a/59df8ca7N7180c35c.jpg","Name":"冬季学生短筒雪地靴女","Introduce":"内里加绒加厚雪地靴，简约百搭，奶奶大棉鞋，妈妈都可以穿的哦。","OldPrice":69.0000,"CouponMoney":30.0000,"CommissionRate":0.200,"ShopTypeId":8,"PeiSongType":"京东","InsertTime":"2017-12-27T10:44:35.92","url":"https://union-click.jd.com/jdc?d=M7XckI","uid":"1000000078","pid":"1113721487","shopid":21772,"shijiancha":174},{"Id":21771,"ImgUrl":"http://img14.360buyimg.com/imgzone/jfs/t10375/50/1873392694/481125/c1df6511/59e8cec1N94335590.jpg","Name":"加绒加厚学生休闲鞋女小白鞋","Introduce":"内里加绒，防滑橡胶底，简约而又百搭的一款小白鞋","OldPrice":69.0000,"CouponMoney":30.0000,"CommissionRate":0.300,"ShopTypeId":8,"PeiSongType":"京东","InsertTime":"2017-12-27T10:44:35.917","url":"https://union-click.jd.com/jdc?d=wQr8CK","uid":"1000000078","pid":"1113721487","shopid":21771,"shijiancha":174},{"Id":21769,"ImgUrl":"http://img14.360buyimg.com/imgzone/jfs/t14848/235/863666108/148360/27f06810/5a3b5edfN61e6085d.jpg","Name":"冬季女包韩版鳄鱼纹单肩包气质百搭斜挎包包","Introduce":"新款女包 现在下单立减50 鳄鱼纹时尚单肩包 支持货到付款 还送运费险","OldPrice":139.0000,"CouponMoney":50.0000,"CommissionRate":0.200,"ShopTypeId":8,"PeiSongType":"京东","InsertTime":"2017-12-27T10:44:35.837","url":"https://union-click.jd.com/jdc?d=9bhAbY","uid":"1000000078","pid":"1113721487","shopid":21769,"shijiancha":174},{"Id":21767,"ImgUrl":"http://img14.360buyimg.com/imgzone/jfs/t15808/223/593662077/103701/c428f2a0/5a371b8eN373bc233.jpg","Name":"北迈2018新款时尚简约双肩包女休闲百搭潮流背包女","Introduce":"实用与时尚并重\n\n以实用为基础的理念设计；优雅的的弧线和优质的\n\n版型，精雕细琢的每一个细节，现成不言而喻的简约时尚","OldPrice":138.0000,"CouponMoney":70.0000,"CommissionRate":0.200,"ShopTypeId":8,"PeiSongType":"京东","InsertTime":"2017-12-27T10:44:35.793","url":"https://union-click.jd.com/jdc?d=5qtAc9","uid":"1000000078","pid":"1113721487","shopid":21767,"shijiancha":174},{"Id":21766,"ImgUrl":"http://img.jingtuitui.com/f86b0201712261143265740.jpg","Name":"牧兽 运动鞋全掌气垫跑步鞋 减震时尚飞线透气","Introduce":"【专营店】掌气垫跑步鞋，时尚飞线透气，防滑耐磨，轻爽透气吸汗，跑步不烧脚，助力避震缓冲，舒适回弹每一步！若非想要尺码或款式，请联系客服或留言！","OldPrice":229.0000,"CouponMoney":100.0000,"CommissionRate":0.200,"ShopTypeId":8,"PeiSongType":"京东","InsertTime":"2017-12-27T10:44:35.697","url":"https://union-click.jd.com/jdc?d=VOJELr","uid":"1000000078","pid":"1113721487","shopid":21766,"shijiancha":174},{"Id":21764,"ImgUrl":"http://img14.360buyimg.com/imgzone/jfs/t16336/20/824019602/238447/ccd9ee3b/5a41f635N5730ff4a.jpg","Name":"石末（SHIMO）休闲鞋","Introduce":"什么时候我们已渐渐习惯被城市冰冷的钢筋水泥束缚住手脚？这个季节，掩藏不住内心的炽热，一起释放，一起出走吧！—— ——石末（SHIMO）休闲鞋","OldPrice":618.0000,"CouponMoney":420.0000,"CommissionRate":0.200,"ShopTypeId":8,"PeiSongType":"京东","InsertTime":"2017-12-27T10:44:35.583","url":"https://union-click.jd.com/jdc?d=wiFZpt","uid":"1000000078","pid":"1113721487","shopid":21764,"shijiancha":174},{"Id":21727,"ImgUrl":"http://img14.360buyimg.com/imgzone/jfs/t14668/203/835650975/568271/f892df3f/5a3b10a9N52203109.jpg","Name":"黄圣依代言 绿茶净痘平衡补水控油面霜","Introduce":"黄圣依代言，控油净痘、补水保湿！买满99元再送修护霜","OldPrice":58.0000,"CouponMoney":20.0000,"CommissionRate":0.300,"ShopTypeId":5,"PeiSongType":"京东","InsertTime":"2017-12-27T10:44:35.56","url":"https://union-click.jd.com/jdc?d=pFKsac","uid":"1000000078","pid":"1113721487","shopid":21727,"shijiancha":174},{"Id":21763,"ImgUrl":"http://img14.360buyimg.com/imgzone/jfs/t12163/79/2542471791/123368/3f6e32ec/5a41f586N001de623.jpg","Name":"石末（SHIMO）休闲鞋","Introduce":"什么时候我们已渐渐习惯被城市冰冷的钢筋水泥束缚住手脚？这个季节，掩藏不住内心的炽热，一起释放，一起出走吧！—— ——石末（SHIMO）休闲鞋","OldPrice":608.0000,"CouponMoney":400.0000,"CommissionRate":0.200,"ShopTypeId":8,"PeiSongType":"京东","InsertTime":"2017-12-27T10:44:35.51","url":"https://union-click.jd.com/jdc?d=uyZkNy","uid":"1000000078","pid":"1113721487","shopid":21763,"shijiancha":174},{"Id":21762,"ImgUrl":"http://img14.360buyimg.com/imgzone/jfs/t14494/244/1019259744/131424/d4e3ef38/5a41f783N313328fd.jpg","Name":"石末（SHIMO）休闲鞋","Introduce":"什么时候我们已渐渐习惯被城市冰冷的钢筋水泥束缚住手脚？这个季节，掩藏不住内心的炽热，一起释放，一起出走吧！—— ——石末（SHIMO）休闲鞋","OldPrice":728.0000,"CouponMoney":470.0000,"CommissionRate":0.200,"ShopTypeId":8,"PeiSongType":"京东","InsertTime":"2017-12-27T10:44:35.503","url":"https://union-click.jd.com/jdc?d=W0pjFA","uid":"1000000078","pid":"1113721487","shopid":21762,"shijiancha":174},{"Id":21761,"ImgUrl":"http://img14.360buyimg.com/imgzone/jfs/t12451/357/2348951181/285352/dfb0b2ac/5a3b72cdN608048f1.jpg","Name":"韩版冬季女包气质百搭手提斜挎包","Introduce":"时尚定型女包 现在下单立减80 支持货到付款 还送运费险","OldPrice":169.0000,"CouponMoney":80.0000,"CommissionRate":0.200,"ShopTypeId":8,"PeiSongType":"京东","InsertTime":"2017-12-27T10:44:35.497","url":"https://union-click.jd.com/jdc?d=eC3HWs","uid":"1000000078","pid":"1113721487","shopid":21761,"shijiancha":174},{"Id":21759,"ImgUrl":"http://img14.360buyimg.com/imgzone/jfs/t12478/12/2506722653/120763/de4edcb5/5a420ae5Ne5ae9782.jpg","Name":"MiNi Cute2017冬季新款休闲皮鞋","Introduce":"MiNi Cute2017冬季新款休闲皮鞋英伦八爪鱼驾车鞋懒人一脚蹬男鞋 新品促销，立减200！数量有限，先到先得！","OldPrice":498.0000,"CouponMoney":200.0000,"CommissionRate":0.200,"ShopTypeId":8,"PeiSongType":"京东","InsertTime":"2017-12-27T10:44:35.47","url":"https://union-click.jd.com/jdc?d=GJmsEE","uid":"1000000078","pid":"1113721487","shopid":21759,"shijiancha":174},{"Id":21758,"ImgUrl":"http://img14.360buyimg.com/imgzone/jfs/t15763/118/907880580/99597/f20ea34d/5a421226N4cd3ebf8.jpg","Name":"MiNi Cute2017冬季新款高帮板鞋","Introduce":"MiNi Cute2017冬季新款高帮板鞋男加绒加绵休闲鞋男士保暖棉鞋学生潮百搭男鞋 新品促销，立减200！数量有限，先到先得！","OldPrice":488.0000,"CouponMoney":200.0000,"CommissionRate":0.200,"ShopTypeId":8,"PeiSongType":"京东","InsertTime":"2017-12-27T10:44:35.417","url":"https://union-click.jd.com/jdc?d=zW1vWL","uid":"1000000078","pid":"1113721487","shopid":21758,"shijiancha":174},{"Id":21723,"ImgUrl":"http://img.jingtuitui.com/99344201712261108068465.jpg","Name":"阿道夫防脱育发姜汁洗发水300ml+植萃护发素248ml","Introduce":"直降21！纯正姜汁，防脱育发，持久留香，植萃精华，深层修护，买1送6！","OldPrice":100.0000,"CouponMoney":21.0000,"CommissionRate":0.200,"ShopTypeId":5,"PeiSongType":"京东","InsertTime":"2017-12-27T10:44:35.417","url":"https://union-click.jd.com/jdc?d=kj8DbI","uid":"1000000078","pid":"1113721487","shopid":21723,"shijiancha":174},{"Id":21757,"ImgUrl":"http://img14.360buyimg.com/imgzone/jfs/t14143/105/1253756663/120577/3c577ce8/5a4201cfN8fe447db.jpg","Name":"马伯新款休闲高帮牛皮鞋男英伦风男靴","Introduce":"马伯  休闲高帮牛皮鞋男   英伦风男靴百搭冬季加绒保暖棉鞋","OldPrice":358.0000,"CouponMoney":200.0000,"CommissionRate":0.200,"ShopTypeId":8,"PeiSongType":"京东","InsertTime":"2017-12-27T10:44:35.37","url":"https://union-click.jd.com/jdc?d=ZN6Eb9","uid":"1000000078","pid":"1113721487","shopid":21757,"shijiancha":174},{"Id":21756,"ImgUrl":"http://img14.360buyimg.com/imgzone/jfs/t13447/232/2580640374/58893/2bc416bb/5a420288Nc48bdacb.jpg","Name":" MiNi Cute2017冬季新款男士休闲板鞋","Introduce":"MiNi Cute2017冬季新款男士休闲皮鞋韩版磨砂皮面小码黑鞋板鞋时尚大码鞋子男 新品促销，立减300，数量有限，先到先得！","OldPrice":598.0000,"CouponMoney":300.0000,"CommissionRate":0.200,"ShopTypeId":8,"PeiSongType":"京东","InsertTime":"2017-12-27T10:44:35.287","url":"https://union-click.jd.com/jdc?d=leqqjh","uid":"1000000078","pid":"1113721487","shopid":21756,"shijiancha":174},{"Id":21755,"ImgUrl":"http://img14.360buyimg.com/imgzone/jfs/t16192/238/876646848/165796/a102dae/5a420805Nbde9fa42.jpg","Name":" MiNi Cute2017新款男鞋","Introduce":"MiNi Cute2017新款男鞋韩版黑色板鞋男圆头系带平底休闲鞋男士青年潮鞋 新品促销，立减200！数量有限，先到先得！","OldPrice":488.0000,"CouponMoney":200.0000,"CommissionRate":0.200,"ShopTypeId":8,"PeiSongType":"京东","InsertTime":"2017-12-27T10:44:35.28","url":"https://union-click.jd.com/jdc?d=QDu9om","uid":"1000000078","pid":"1113721487","shopid":21755,"shijiancha":174},{"Id":21754,"ImgUrl":"http://img14.360buyimg.com/imgzone/jfs/t15568/73/892981024/127702/d2b217a2/5a420534N3deb4067.jpg","Name":"马伯男士休闲鞋时尚真皮马丁靴保暖男鞋 ","Introduce":"马伯  新品男士休闲鞋时尚真皮马丁靴男   加绒靴子欧美保暖男鞋","OldPrice":518.0000,"CouponMoney":300.0000,"CommissionRate":0.200,"ShopTypeId":8,"PeiSongType":"京东","InsertTime":"2017-12-27T10:44:35.19","url":"https://union-click.jd.com/jdc?d=sJW4FP","uid":"1000000078","pid":"1113721487","shopid":21754,"shijiancha":174},{"Id":21753,"ImgUrl":"http://img14.360buyimg.com/imgzone/jfs/t13891/283/2508078697/181963/b0809814/5a41fed9N1456803f.jpg","Name":"马伯冬季新款韩版潮流猪皮休闲板鞋男","Introduce":"马伯  新款韩版潮流休闲鞋   男士英伦猪皮百搭板鞋男嘻哈潮男鞋","OldPrice":258.0000,"CouponMoney":110.0000,"CommissionRate":0.200,"ShopTypeId":8,"PeiSongType":"京东","InsertTime":"2017-12-27T10:44:35.187","url":"https://union-click.jd.com/jdc?d=SAUScp","uid":"1000000078","pid":"1113721487","shopid":21753,"shijiancha":174},{"Id":21751,"ImgUrl":"http://img14.360buyimg.com/imgzone/jfs/t12394/69/2466627763/186109/6e003645/5a40beb1N549965c1.jpg","Name":"韩版ulzzang运动鞋女","Introduce":"【大牌同款】超高性价比即可拿到大牌同款运动鞋，地摊价格，商城品质！","OldPrice":228.0000,"CouponMoney":50.0000,"CommissionRate":0.200,"ShopTypeId":8,"PeiSongType":"京东","InsertTime":"2017-12-27T10:44:35.107","url":"https://union-click.jd.com/jdc?d=HZgM3n","uid":"1000000078","pid":"1113721487","shopid":21751,"shijiancha":174},{"Id":21748,"ImgUrl":"http://img14.360buyimg.com/imgzone/jfs/t13888/84/2440736778/172372/495a6faa/5a405d90N01c32a03.jpg","Name":"梵谷男士钱包迷你短款多卡位卡包","Introduce":"多卡位大容量 搭扣设计更安全 低价冲销量，二层牛皮，质量信得过","OldPrice":79.0000,"CouponMoney":10.0000,"CommissionRate":0.200,"ShopTypeId":8,"PeiSongType":"京东","InsertTime":"2017-12-27T10:44:34.86","url":"https://union-click.jd.com/jdc?d=GXueqb","uid":"1000000078","pid":"1113721487","shopid":21748,"shijiancha":174},{"Id":21745,"ImgUrl":"http://img14.360buyimg.com/imgzone/jfs/t16534/353/869671415/116635/733a7365/5a4207d0Nfbec4a73.jpg","Name":"马伯2017冬季新款潮鞋牛皮休闲鞋男鞋","Introduce":"马伯   冬季新款潮鞋休闲鞋男鞋   耐磨韩版时尚牛皮潮流黑色鞋子男潮","OldPrice":358.0000,"CouponMoney":200.0000,"CommissionRate":0.200,"ShopTypeId":8,"PeiSongType":"京东","InsertTime":"2017-12-27T10:44:34.657","url":"https://union-click.jd.com/jdc?d=slgGDo","uid":"1000000078","pid":"1113721487","shopid":21745,"shijiancha":174},{"Id":21744,"ImgUrl":"http://img14.360buyimg.com/imgzone/jfs/t14563/265/1021967969/95198/c1d8cf09/5a420988Nc1f5aba8.jpg","Name":"马伯新款英伦鳄鱼纹真皮休闲皮鞋男","Introduce":"马伯   新款英伦低帮休闲鞋男鞋鳄鱼纹真皮皮鞋   男士青年一脚蹬板鞋男","OldPrice":508.0000,"CouponMoney":300.0000,"CommissionRate":0.200,"ShopTypeId":8,"PeiSongType":"京东","InsertTime":"2017-12-27T10:44:34.547","url":"https://union-click.jd.com/jdc?d=RGjPko","uid":"1000000078","pid":"1113721487","shopid":21744,"shijiancha":174},{"Id":21709,"ImgUrl":"http://img14.360buyimg.com/imgzone/jfs/t13414/335/1881106594/520646/86759dca/5a2ca900N355bfd98.jpg","Name":"皲裂膏马油手足防冻霜去脚气防龟裂冻疮膏","Introduce":"冬季常备，防龟裂干裂脱皮冻疮膏马油使用方便","OldPrice":49.0000,"CouponMoney":30.0000,"CommissionRate":0.200,"ShopTypeId":5,"PeiSongType":"京东","InsertTime":"2017-12-27T10:44:34.253","url":"https://union-click.jd.com/jdc?d=9G1JSu","uid":"1000000078","pid":"1113721487","shopid":21709,"shijiancha":174},{"Id":21705,"ImgUrl":"http://img.jingtuitui.com/1785a201712261621022427.jpg","Name":"云南白药卷纸55g*12卷不漂白食品级本色纸便携式","Introduce":"云南白药本色竹纤维纸，不漂白天然抑菌，孕婴适用，食品级无添加，湿水承受20个硬币不破，便携式小包装。\n","OldPrice":29.9000,"CouponMoney":10.0000,"CommissionRate":0.200,"ShopTypeId":5,"PeiSongType":"京东","InsertTime":"2017-12-27T10:44:33.887","url":"https://union-click.jd.com/jdc?d=RTr3ec","uid":"1000000078","pid":"1113721487","shopid":21705,"shijiancha":174},{"Id":21612,"ImgUrl":"http://img14.360buyimg.com/imgzone/jfs/t13234/275/2406328538/328373/f1e3570a/5a420e15N71920cd2.jpg","Name":"糖果盒 创意过年分格带盖干果盘家用客厅果盘","Introduce":"优质选材，健康安全 欧式炫彩设计，多功能收纳更省空间","OldPrice":59.0000,"CouponMoney":10.0000,"CommissionRate":0.200,"ShopTypeId":7,"PeiSongType":"京东","InsertTime":"2017-12-27T10:44:33.857","url":"https://union-click.jd.com/jdc?d=05J1fw","uid":"1000000078","pid":"1113721487","shopid":21612,"shijiancha":174},{"Id":21611,"ImgUrl":"http://img14.360buyimg.com/imgzone/jfs/t15973/249/878996834/375588/956c60c5/5a41e1c5N5341b2c0.jpg","Name":" 糖果盒 家用客厅创意干果盘过年分格带盖糖果盘","Introduce":"优质选材，一盘多用，分格带盖，防潮防尘，外加卡扣设计 ","OldPrice":25.8000,"CouponMoney":4.0000,"CommissionRate":0.200,"ShopTypeId":7,"PeiSongType":"京东","InsertTime":"2017-12-27T10:44:33.777","url":"https://union-click.jd.com/jdc?d=FiL626","uid":"1000000078","pid":"1113721487","shopid":21611,"shijiancha":174},{"Id":21741,"ImgUrl":"http://img.jingtuitui.com/e40ea201712261757321.jpg","Name":"【大牌来袭】高尔夫双肩背包 ","Introduce":"搞事情啊！这么可爱的名牌包包，只要79，帅哥美女们，赶紧撸起来！【送运费险】","OldPrice":189.0000,"CouponMoney":110.0000,"CommissionRate":0.300,"ShopTypeId":8,"PeiSongType":"京东","InsertTime":"2017-12-27T10:44:33.717","url":"https://union-click.jd.com/jdc?d=q8abU6","uid":"1000000078","pid":"1113721487","shopid":21741,"shijiancha":174},{"Id":21702,"ImgUrl":"http://img14.360buyimg.com/imgzone/jfs/t10684/267/324957457/437872/dbcbff38/59cbccaeN9083cea6.jpg","Name":"【5支装】葆玛蕾敦 维生素口红套装","Introduce":"一顿午饭钱够你浪一年！一次购买，低调席卷今年必备色号！天然成分，安心上唇，不脱色，不沾杯，你值得拥有！","OldPrice":49.0000,"CouponMoney":20.0000,"CommissionRate":0.500,"ShopTypeId":5,"PeiSongType":"京东","InsertTime":"2017-12-27T10:44:33.69","url":"https://union-click.jd.com/jdc?d=w3nIh3","uid":"1000000078","pid":"1113721487","shopid":21702,"shijiancha":174},{"Id":21740,"ImgUrl":"http://img14.360buyimg.com/imgzone/jfs/t6094/202/2266318889/185141/68ebb0e9/593e1551N9b6da76f.jpg","Name":"运动鞋全掌气垫跑步鞋 时尚飞线减震","Introduce":"【专营店】掌气垫跑步鞋，时尚飞线透气，防滑耐磨，轻爽透气吸汗，跑步不烧脚，助力避震缓冲，舒适回弹每一步！若非想要尺码或款式，请联系客服或留言！","OldPrice":229.0000,"CouponMoney":100.0000,"CommissionRate":0.200,"ShopTypeId":8,"PeiSongType":"京东","InsertTime":"2017-12-27T10:44:33.573","url":"https://union-click.jd.com/jdc?d=OW7lVd","uid":"1000000078","pid":"1113721487","shopid":21740,"shijiancha":174},{"Id":21739,"ImgUrl":"http://img14.360buyimg.com/imgzone/jfs/t13885/114/2353413309/309870/3fd22ab0/5a3a08bdNee5739bc.jpg","Name":"雪地靴","Introduce":"女短筒加厚冬季加绒保暖雪地棉纽扣平底女鞋子","OldPrice":158.0000,"CouponMoney":10.0000,"CommissionRate":0.200,"ShopTypeId":8,"PeiSongType":"京东","InsertTime":"2017-12-27T10:44:33.5","url":"","uid":"1000000078","pid":"1113721487","shopid":21739,"shijiancha":174},{"Id":21602,"ImgUrl":"http://img14.360buyimg.com/imgzone/jfs/t15964/47/498664658/175265/352cfacb/5a332f1dN5889c4a7.jpg","Name":" 门扉 马桶垫 加厚毛绒坐垫卡通保暖马桶坐垫","Introduce":"底部PU材质！尺寸约42*35cm，边宽9cm！柔软保暖！","OldPrice":39.0000,"CouponMoney":9.0000,"CommissionRate":0.200,"ShopTypeId":7,"PeiSongType":"京东","InsertTime":"2017-12-27T10:44:33.033","url":"https://union-click.jd.com/jdc?d=aI1iWY","uid":"1000000078","pid":"1113721487","shopid":21602,"shijiancha":174},{"Id":21601,"ImgUrl":"http://img.jingtuitui.com/0251f201712041447399131.jpg","Name":"久量 人体感应小夜灯 宝宝婴儿喂奶灯 楼道感应起夜灯","Introduce":"人体感应夜灯，光线柔和不刺眼，让宝宝安心睡眠，适用于过道走廊橱柜宝宝房衣柜玄关等，人来即亮人走即灭~~卷后12.9！","OldPrice":29.9000,"CouponMoney":17.0000,"CommissionRate":0.200,"ShopTypeId":7,"PeiSongType":"京东","InsertTime":"2017-12-27T10:44:32.953","url":"https://union-click.jd.com/jdc?d=fYanDW","uid":"1000000078","pid":"1113721487","shopid":21601,"shijiancha":174},{"Id":21600,"ImgUrl":"http://img14.360buyimg.com/imgzone/jfs/t12652/318/1861780443/262191/50c9d5aa/5a2b4d4cN2fedbe41.jpg","Name":"门扉 儿童凳子 塑料可折叠板凳浴室小板凳儿童矮凳","Introduce":"不用时可折叠，创意提手设计！加厚pp材质，简约大方！","OldPrice":39.0000,"CouponMoney":9.0000,"CommissionRate":0.200,"ShopTypeId":7,"PeiSongType":"京东","InsertTime":"2017-12-27T10:44:32.857","url":"https://union-click.jd.com/jdc?d=A57XpI","uid":"1000000078","pid":"1113721487","shopid":21600,"shijiancha":174},{"Id":21599,"ImgUrl":"http://img14.360buyimg.com/imgzone/jfs/t6247/182/596690316/191596/dd631f9e/5942283fNebb7746f.jpg","Name":"门扉 玩具收纳箱 卡通儿童玩具收纳箱塑料加厚整理箱","Introduce":"多种尺寸，卡通造型！提手设计，方便移动！不易变形，多功能收纳！","OldPrice":39.0000,"CouponMoney":9.0000,"CommissionRate":0.200,"ShopTypeId":7,"PeiSongType":"京东","InsertTime":"2017-12-27T10:44:32.83","url":"https://union-click.jd.com/jdc?d=BWhBWq","uid":"1000000078","pid":"1113721487","shopid":21599,"shijiancha":174},{"Id":21598,"ImgUrl":"http://img14.360buyimg.com/imgzone/jfs/t4630/207/427759899/185031/a993a99d/58cfa2f0N1cd3ec1d.jpg","Name":"门扉 大米桶 塑料储米箱米缸面粉箱加厚带盖","Introduce":"带盖密封，优良pp，厨房多功能收纳箱，你值得拥有！","OldPrice":39.0000,"CouponMoney":9.0000,"CommissionRate":0.200,"ShopTypeId":7,"PeiSongType":"京东","InsertTime":"2017-12-27T10:44:32.82","url":"https://union-click.jd.com/jdc?d=5Hbv1a","uid":"1000000078","pid":"1113721487","shopid":21598,"shijiancha":174},{"Id":21596,"ImgUrl":"http://img14.360buyimg.com/imgzone/jfs/t10240/324/1899318267/213847/45c4bb53/59eb04e7N29a70f8b.jpg","Name":"速来抢购【2600毫升】冬季养生陶瓷汤锅锅 双耳炖锅","Introduce":"汤锅汤煲大沙锅 升级款 砂锅炖锅陶瓷煲汤锅","OldPrice":69.9000,"CouponMoney":30.0000,"CommissionRate":0.200,"ShopTypeId":7,"PeiSongType":"京东","InsertTime":"2017-12-27T10:44:32.69","url":"https://union-click.jd.com/jdc?d=FXJWbk","uid":"1000000078","pid":"1113721487","shopid":21596,"shijiancha":174},{"Id":21591,"ImgUrl":"http://img14.360buyimg.com/imgzone/jfs/t13978/264/2524699004/405637/cdb83000/5a41efcbNbef661ac.jpg","Name":"不锈钢削皮器多功能","Introduce":"树镇（SHUZHEN） 不锈钢削皮器多功能瓜刨刀笑脸双头刨子削皮刀削皮器刮皮器水果刀","OldPrice":9.9000,"CouponMoney":1.0000,"CommissionRate":0.200,"ShopTypeId":7,"PeiSongType":"京东","InsertTime":"2017-12-27T10:44:32.347","url":"https://union-click.jd.com/jdc?d=DSbXLW","uid":"1000000078","pid":"1113721487","shopid":21591,"shijiancha":174},{"Id":21685,"ImgUrl":"http://img14.360buyimg.com/imgzone/jfs/t6130/27/4423338657/641527/ac93f3ba/59633b60N42dd5329.jpg","Name":"韩后达人面膜补水保湿面贴膜23片 ","Introduce":"京东配送，补水保湿，亮白清透，敷出水润精致嫩白肌，给您的肌肤最全面的呵护！\n","OldPrice":128.0000,"CouponMoney":32.0000,"CommissionRate":0.200,"ShopTypeId":5,"PeiSongType":"京东配送","InsertTime":"2017-12-27T10:44:31.803","url":"https://union-click.jd.com/jdc?d=SlZ6MK","uid":"1000000078","pid":"1113721487","shopid":21685,"shijiancha":174},{"Id":21581,"ImgUrl":"http://img14.360buyimg.com/imgzone/jfs/t12484/250/847119891/282717/b65e9f8a/5a152310Nc9416a61.jpg","Name":"门扉 儿童凳子 可爱创意塑料小凳子加厚折叠凳","Introduce":"加厚pp，承重性好！折叠拆卸，方便携带！收纳简单，不占空间！","OldPrice":39.0000,"CouponMoney":9.0000,"CommissionRate":0.200,"ShopTypeId":7,"PeiSongType":"京东","InsertTime":"2017-12-27T10:44:31.613","url":"https://union-click.jd.com/jdc?d=xH19MP","uid":"1000000078","pid":"1113721487","shopid":21581,"shijiancha":174},{"Id":21579,"ImgUrl":"http://img14.360buyimg.com/imgzone/jfs/t11323/162/1309226475/386759/9c06de/5a422a5cNd549d1b0.jpg","Name":" 魔法扫把 家用清洁海绵扫帚 卫生间地板刮水器 玻璃刮 ","Introduce":"优质选材，生活实用派，可180度旋转，轻松清理毛发、灰尘、水渍","OldPrice":19.9000,"CouponMoney":4.0000,"CommissionRate":0.200,"ShopTypeId":7,"PeiSongType":"京东","InsertTime":"2017-12-27T10:44:31.447","url":"https://union-click.jd.com/jdc?d=ppLSnT","uid":"1000000078","pid":"1113721487","shopid":21579,"shijiancha":174},{"Id":21646,"ImgUrl":"http://img14.360buyimg.com/imgzone/jfs/t12310/317/525499277/482911/825ece98/5a2cfc47Nc3e2e6c6.jpg","Name":"小牛顿科学馆全10册 儿童3-6岁科普绘本 十万个为什么","Introduce":"全套10册，宝宝的第一套科普绘本，选取孩子感兴趣的话题，解决孩子喜欢问家长答不上来的难题。","OldPrice":36.8000,"CouponMoney":13.0000,"CommissionRate":0.200,"ShopTypeId":10,"PeiSongType":"京东","InsertTime":"2017-12-27T10:44:31.373","url":"https://union-click.jd.com/jdc?d=Q01ZtB","uid":"1000000078","pid":"1113721487","shopid":21646,"shijiancha":174},{"Id":21645,"ImgUrl":"http://img14.360buyimg.com/imgzone/jfs/t14518/133/447657438/299322/8c40a507/5a2cfc59N93b3957f.jpg","Name":" 365夜天天好故事 彩图注音版婴儿故事书0-3岁","Introduce":"全套4册 200多个故事陪伴宝宝成长，质量好，大字不伤眼，精彩的故事，能启迪孩子的智慧。","OldPrice":32.8000,"CouponMoney":13.0000,"CommissionRate":0.200,"ShopTypeId":10,"PeiSongType":"京东","InsertTime":"2017-12-27T10:44:31.327","url":"https://union-click.jd.com/jdc?d=rYyMKr","uid":"1000000078","pid":"1113721487","shopid":21645,"shijiancha":174},{"Id":21639,"ImgUrl":"http://img14.360buyimg.com/imgzone/jfs/t7891/232/3985223939/325575/ccb81e14/5a02a9a2N078ac953.jpg","Name":"吻猪水晶香水座","Introduce":"水晶情侣对吻猪，礼盒包装，赠送香水补充液和双面胶！","OldPrice":35.0000,"CouponMoney":6.0000,"CommissionRate":0.200,"ShopTypeId":10,"PeiSongType":"京东","InsertTime":"2017-12-27T10:44:30.983","url":"https://union-click.jd.com/jdc?d=SIp9u3","uid":"1000000078","pid":"1113721487","shopid":21639,"shijiancha":174},{"Id":21629,"ImgUrl":"http://img14.360buyimg.com/imgzone/jfs/t2713/95/3520270741/156173/5e38e608/57916a3aNa64186be.jpg","Name":"不打不骂教男孩100招","Introduce":"《不打不骂教男孩100招》通过众多事例，全面分析了男孩独特的个性特征与心理特征，为您提供100招教育方法，助您将您的儿子培养成有个性、独立、自主、坚强的男孩！","OldPrice":28.9000,"CouponMoney":12.0000,"CommissionRate":0.300,"ShopTypeId":10,"PeiSongType":"京东","InsertTime":"2017-12-27T10:44:30.323","url":"https://union-click.jd.com/jdc?d=Mrz923","uid":"1000000078","pid":"1113721487","shopid":21629,"shijiancha":174},{"Id":21567,"ImgUrl":"http://img.jingtuitui.com/6bf4c201712270837165678.jpg","Name":"围裙 厨房双肩无袖防水围裙 ","Introduce":"厨房双肩无袖防水围裙，防水防污，简约大方，材质优良，做工精细，轻盈耐脏！","OldPrice":39.0000,"CouponMoney":22.0000,"CommissionRate":0.200,"ShopTypeId":7,"PeiSongType":"京东","InsertTime":"2017-12-27T10:44:30.257","url":"https://union-click.jd.com/jdc?d=NDkHUL","uid":"1000000078","pid":"1113721487","shopid":21567,"shijiancha":174},{"Id":21565,"ImgUrl":"http://img14.360buyimg.com/imgzone/jfs/t14854/320/867653968/386540/b726ecc4/5a3b8b44Nada62569.jpg","Name":"创意保温杯 时尚男女真空不锈钢 情侣学生携茶杯","Introduce":"创意保温杯 时尚男女真空不锈钢 情侣学生携茶杯 保温杯女","OldPrice":29.0000,"CouponMoney":5.0000,"CommissionRate":0.200,"ShopTypeId":7,"PeiSongType":"京东","InsertTime":"2017-12-27T10:44:30.237","url":"https://union-click.jd.com/jdc?d=tJr6ta","uid":"1000000078","pid":"1113721487","shopid":21565,"shijiancha":174},{"Id":21628,"ImgUrl":"http://img14.360buyimg.com/imgzone/jfs/t6076/115/6982137973/298607/14789e66/59793e80N4b37585c.jpg","Name":"伴君汽车香水挂件","Introduce":"好车配好香，恰如宝剑配英雄 香薰精油采用优质纯植物提取 通过风口，散发到车内，整个过程还原植物特性","OldPrice":45.0000,"CouponMoney":15.0000,"CommissionRate":0.200,"ShopTypeId":10,"PeiSongType":"京东","InsertTime":"2017-12-27T10:44:30.187","url":"https://union-click.jd.com/jdc?d=EA6uqY","uid":"1000000078","pid":"1113721487","shopid":21628,"shijiancha":174},{"Id":21564,"ImgUrl":"http://img14.360buyimg.com/imgzone/jfs/t12775/163/1758899119/381857/4b18abc4/5a28d494N55f55978.jpg","Name":"小毛毯盖腿午睡毯 办公室盖毯 单人膝盖毯","Introduce":"小毛毯盖腿午睡毯 办公室盖毯 单人膝盖毯","OldPrice":24.8000,"CouponMoney":5.0000,"CommissionRate":0.200,"ShopTypeId":7,"PeiSongType":"京东","InsertTime":"2017-12-27T10:44:30.153","url":"https://union-click.jd.com/jdc?d=3T5tXQ","uid":"1000000078","pid":"1113721487","shopid":21564,"shijiancha":174},{"Id":21562,"ImgUrl":"http://img14.360buyimg.com/imgzone/jfs/t12430/166/1718897534/188221/38b0d1d6/5a266357N0c49377c.jpg","Name":"法莱绒双人枕套","Introduce":"法莱绒双人枕套  冬季加厚保暖情侣法兰绒长枕头套","OldPrice":43.8000,"CouponMoney":8.0000,"CommissionRate":0.200,"ShopTypeId":7,"PeiSongType":"京东","InsertTime":"2017-12-27T10:44:30.137","url":"https://union-click.jd.com/jdc?d=1zg2VQ","uid":"1000000078","pid":"1113721487","shopid":21562,"shijiancha":174},{"Id":21627,"ImgUrl":"http://img.jingtuitui.com/27dd5201710231136401148.jpg","Name":"招财貔貅汽车挂件 创意设计 行车保平安","Introduce":"貔貅有嘴无肛，能吞天下财而不 漏，只进不出、神通特异，故有招财进宝、吸纳四方之财的寓意，同时也有赶走邪气 、带来好运的作用  ","OldPrice":39.0000,"CouponMoney":15.0000,"CommissionRate":0.250,"ShopTypeId":10,"PeiSongType":"京东","InsertTime":"2017-12-27T10:44:30.103","url":"https://union-click.jd.com/jdc?d=3X6VRN","uid":"1000000078","pid":"1113721487","shopid":21627,"shijiancha":174},{"Id":21626,"ImgUrl":"http://img.jingtuitui.com/de859201712141502111459.jpg","Name":"驾驶证皮套","Introduce":"皮质卡包，手感柔软，多色可选，耐磨耐用，性价比之王!","OldPrice":19.9000,"CouponMoney":5.0000,"CommissionRate":0.200,"ShopTypeId":10,"PeiSongType":"京东","InsertTime":"2017-12-27T10:44:30.097","url":"https://union-click.jd.com/jdc?d=Rrpuq0","uid":"1000000078","pid":"1113721487","shopid":21626,"shijiancha":174},{"Id":21625,"ImgUrl":"http://img14.360buyimg.com/imgzone/jfs/t10552/339/961936310/203636/c1eacadc/59dae6e0N6233a6d1.jpg","Name":"方向盘套四季通用","Introduce":"防滑纹路，耐磨皮革，握感十足，带来舒适的驾驭体验！适用于98%车型，下单备注车型年份即可！","OldPrice":46.0000,"CouponMoney":7.0000,"CommissionRate":0.200,"ShopTypeId":10,"PeiSongType":"京东","InsertTime":"2017-12-27T10:44:30.027","url":"https://union-click.jd.com/jdc?d=La2rMf","uid":"1000000078","pid":"1113721487","shopid":21625,"shijiancha":174},{"Id":21560,"ImgUrl":"http://img.jingtuitui.com/a0a9f201712270840233841.jpg","Name":"橱柜垃圾桶 家用厨房门挂式收纳桶 ","Introduce":"多功能厨房垃圾桶，挂钩设计，方便取放，磨砂手感材质，家居必备神器！","OldPrice":39.0000,"CouponMoney":23.0000,"CommissionRate":0.200,"ShopTypeId":7,"PeiSongType":"京东","InsertTime":"2017-12-27T10:44:29.917","url":"https://union-click.jd.com/jdc?d=hlYHVn","uid":"1000000078","pid":"1113721487","shopid":21560,"shijiancha":174},{"Id":21558,"ImgUrl":"http://img14.360buyimg.com/imgzone/jfs/t16570/27/449597726/344731/831b6f3c/5a3720deNb981a7ce.jpg","Name":"门扉 被子收纳袋 整理袋 储物袋","Introduce":"实用收纳袋，无纺布多彩竹炭，便携提取，简易折叠，方便存放，减少占用空间！","OldPrice":39.0000,"CouponMoney":22.0000,"CommissionRate":0.200,"ShopTypeId":7,"PeiSongType":"京东","InsertTime":"2017-12-27T10:44:29.893","url":"https://union-click.jd.com/jdc?d=5vay8E","uid":"1000000078","pid":"1113721487","shopid":21558,"shijiancha":174},{"Id":21557,"ImgUrl":"http://img.jingtuitui.com/3409b201712270851271443.jpg","Name":"早餐杯神器蛋卷机 多功能料理大师 杯型煎蛋器 ","Introduce":"鸡蛋新做法，早餐随心弄 营养早餐 健康身体","OldPrice":99.0000,"CouponMoney":40.0000,"CommissionRate":0.200,"ShopTypeId":7,"PeiSongType":"京东","InsertTime":"2017-12-27T10:44:29.887","url":"https://union-click.jd.com/jdc?d=dGMEU8","uid":"1000000078","pid":"1113721487","shopid":21557,"shijiancha":174},{"Id":21623,"ImgUrl":"http://img14.360buyimg.com/imgzone/jfs/t14965/63/439141162/194897/78947f5c/5a2cfc50Nebb3082b.jpg","Name":"高尔基三部曲全3册 童年 在人间 我的大学 初中小学版","Introduce":"全套3册经过作者精心翻译做到既不失本意有又优美流畅，此三部弥漫凄惨，压力，却仍旧带来力量和生机的书。","OldPrice":29.8000,"CouponMoney":10.0000,"CommissionRate":0.200,"ShopTypeId":10,"PeiSongType":"京东","InsertTime":"2017-12-27T10:44:29.793","url":"https://union-click.jd.com/jdc?d=UbXwG3","uid":"1000000078","pid":"1113721487","shopid":21623,"shijiancha":174},{"Id":21622,"ImgUrl":"http://img14.360buyimg.com/imgzone/jfs/t15802/126/284029936/337989/5ffbd0c4/5a2cfc54N7d4ef962.jpg","Name":"爱上优秀的自己全10册 3-6岁儿童情商培养","Introduce":"满满正能量，给孩子无尽的精神财富。帮孩子树立一个好个性，好习惯。","OldPrice":29.8000,"CouponMoney":10.0000,"CommissionRate":0.200,"ShopTypeId":10,"PeiSongType":"京东","InsertTime":"2017-12-27T10:44:29.79","url":"https://union-click.jd.com/jdc?d=vamOzr","uid":"1000000078","pid":"1113721487","shopid":21622,"shijiancha":174},{"Id":21552,"ImgUrl":"http://img.jingtuitui.com/25466201712270911298591.jpg","Name":"明哲家纺 抱枕 卡通亚麻风格","Introduce":"卡通棉麻抱枕靠垫，多种花色图案可选，舒适百搭透气 45cm*45cm\n","OldPrice":39.9000,"CouponMoney":20.0000,"CommissionRate":0.200,"ShopTypeId":7,"PeiSongType":"京东","InsertTime":"2017-12-27T10:44:29.527","url":"https://union-click.jd.com/jdc?d=lBLhiS","uid":"1000000078","pid":"1113721487","shopid":21552,"shijiancha":174},{"Id":21551,"ImgUrl":"http://img.jingtuitui.com/c25ad201712270903563166.jpg","Name":"门扉 干果盘 客厅居家果盘拼盒 零食盒","Introduce":"创意分格零食盒，严密盖封，防潮防尘防串味，PP材质，多色可选！","OldPrice":39.0000,"CouponMoney":20.0000,"CommissionRate":0.200,"ShopTypeId":7,"PeiSongType":"京东","InsertTime":"2017-12-27T10:44:29.483","url":"https://union-click.jd.com/jdc?d=SI6nQo","uid":"1000000078","pid":"1113721487","shopid":21551,"shijiancha":174},{"Id":21549,"ImgUrl":"http://img14.360buyimg.com/imgzone/jfs/t12334/56/1689736758/410910/6c3b9ff/5a276200Nc41425e2.jpg","Name":"超厚防水PU皮革防寒连体保暖挡风被","Introduce":"皮尤面料防水防寒。内丹为加厚毛毡，内衬为成品毛毯毛绒超厚。保暖性是一般的三倍","OldPrice":69.9000,"CouponMoney":10.0000,"CommissionRate":0.200,"ShopTypeId":7,"PeiSongType":"京东","InsertTime":"2017-12-27T10:44:29.473","url":"https://union-click.jd.com/jdc?d=M6OMqA","uid":"1000000078","pid":"1113721487","shopid":21549,"shijiancha":174},{"Id":21618,"ImgUrl":"http://img14.360buyimg.com/imgzone/jfs/t15970/344/281170753/376676/7a55a7db/5a2cfc53N02221a9b.jpg","Name":"弟子规三字经唐诗论语故事书唐诗三百首幼儿早教书","Introduce":"全套4册，大字正文注音版，方便阅读，精美插图 精彩解读 译文，让孩子更深入的理解。","OldPrice":35.8000,"CouponMoney":16.0000,"CommissionRate":0.200,"ShopTypeId":10,"PeiSongType":"京东","InsertTime":"2017-12-27T10:44:29.45","url":"https://union-click.jd.com/jdc?d=XWCtM5","uid":"1000000078","pid":"1113721487","shopid":21618,"shijiancha":174},{"Id":21543,"ImgUrl":"http://img.jingtuitui.com/98b5a20171227101141991.jpg","Name":"禾艾苏（heisou）2000ml大容量玻璃茶壶茶具","Introduce":"一提一倒，壶口出水流畅集中不外溅。时尚泡茶壶，居家、办公、会所等一壶多用！","OldPrice":39.0000,"CouponMoney":10.0000,"CommissionRate":0.200,"ShopTypeId":7,"PeiSongType":"京东","InsertTime":"2017-12-27T10:44:29.107","url":"https://union-click.jd.com/jdc?d=qaA7Dy","uid":"1000000078","pid":"1113721487","shopid":21543,"shijiancha":174},{"Id":21614,"ImgUrl":"http://img14.360buyimg.com/imgzone/jfs/t15841/28/307591041/362093/a9aa0b69/5a2cfc5aN683b9282.jpg","Name":"中国名人故事绘本全10册 中英双语注音版","Introduce":"全套10册，采用中英双语注音，在阅读中提升语言能力，充满力量的文字，激励孩子去面对困难挑战。","OldPrice":29.8000,"CouponMoney":10.0000,"CommissionRate":0.200,"ShopTypeId":10,"PeiSongType":"京东","InsertTime":"2017-12-27T10:44:28.99","url":"https://union-click.jd.com/jdc?d=U58CYp","uid":"1000000078","pid":"1113721487","shopid":21614,"shijiancha":174},{"Id":21540,"ImgUrl":"http://img14.360buyimg.com/imgzone/jfs/t14053/342/2150664657/188882/665b22fc/5a377d87N9f9e5fd8.jpg","Name":" 白领公社 干果盒 多格糖果盒密封果盘","Introduce":"多格糖果盒密封果盘坚果结婚糖果盘春节水果盘零食收纳盒 圆形粉色玫瑰\n","OldPrice":59.0000,"CouponMoney":13.0000,"CommissionRate":0.200,"ShopTypeId":7,"PeiSongType":"京东","InsertTime":"2017-12-27T10:44:28.943","url":"https://union-click.jd.com/jdc?d=kh3fmq","uid":"1000000078","pid":"1113721487","shopid":21540,"shijiancha":174},{"Id":21539,"ImgUrl":"http://img.jingtuitui.com/563ad201712271028481210.jpg","Name":"【品质之选】时尚立体孔雀钟","Introduce":"这么便宜你都卖，居然还包邮！领券满减才78，精工细刻，3色可选，不仅是挂钟更是一件艺术品！为你打造视觉盛宴！","OldPrice":178.0000,"CouponMoney":100.0000,"CommissionRate":0.300,"ShopTypeId":7,"PeiSongType":"京东","InsertTime":"2017-12-27T10:44:28.823","url":"https://union-click.jd.com/jdc?d=P3N9i0","uid":"1000000078","pid":"1113721487","shopid":21539,"shijiancha":174},{"Id":21526,"ImgUrl":"http://img14.360buyimg.com/imgzone/jfs/t12271/112/1655585899/212765/1f5a3d44/5a261398N7a74cc13.jpg","Name":"羊绒护膝","Introduce":"羊绒护膝保暖老寒腿女男冬季中老年炎加长款护漆盖防寒护腿套袜套","OldPrice":88.0000,"CouponMoney":10.0000,"CommissionRate":0.200,"ShopTypeId":9,"PeiSongType":"京东","InsertTime":"2017-12-27T10:44:28.307","url":"https://union-click.jd.com/jdc?d=6atwtP","uid":"1000000078","pid":"1113721487","shopid":21526,"shijiancha":174},{"Id":21527,"ImgUrl":"http://img14.360buyimg.com/imgzone/jfs/t13801/149/2449315481/302055/fd6e25ec/5a3f4207Nc641c498.jpg","Name":"健腹轮巨轮","Introduce":"轮家用静音健身器材男女滚轮腹肌训练器收腹器 ","OldPrice":498.0000,"CouponMoney":50.0000,"CommissionRate":0.200,"ShopTypeId":9,"PeiSongType":"京东","InsertTime":"2017-12-27T10:44:28.307","url":"https://union-click.jd.com/jdc?d=CBp0n4","uid":"1000000078","pid":"1113721487","shopid":21527,"shijiancha":174},{"Id":21520,"ImgUrl":"http://img14.360buyimg.com/imgzone/jfs/t14908/187/1025386196/357401/b5e9528a/5a41b554N68195d46.jpg","Name":"新款冬装棉衣外套","Introduce":"修身版型，型动自如，彰显男人魅力型感。  让你不在为好看而瑟瑟发抖。","OldPrice":389.0000,"CouponMoney":200.0000,"CommissionRate":0.200,"ShopTypeId":2,"PeiSongType":"京东","InsertTime":"2017-12-27T10:44:25.467","url":"https://union-click.jd.com/jdc?d=ZrMetu","uid":"1000000078","pid":"1113721487","shopid":21520,"shijiancha":174},{"Id":21521,"ImgUrl":"http://img14.360buyimg.com/imgzone/jfs/t14407/241/997832010/333833/e80cfeb6/5a41ae45N905b9e8c.jpg","Name":"新款加绒男士夹克","Introduce":"时尚并存岂止于经典，华丽而不张扬，穿着帅气有型。","OldPrice":325.0000,"CouponMoney":200.0000,"CommissionRate":0.200,"ShopTypeId":2,"PeiSongType":"京东","InsertTime":"2017-12-27T10:44:25.467","url":"https://union-click.jd.com/jdc?d=QS4UaB","uid":"1000000078","pid":"1113721487","shopid":21521,"shijiancha":174},{"Id":21519,"ImgUrl":"http://img.jingtuitui.com/538dc201712261142469825.jpg","Name":"花花公子冬季新款男士高领毛衣纯色","Introduce":"爆款推荐！ 花花公子冬季新款男士高领毛衣纯色","OldPrice":128.0000,"CouponMoney":59.0000,"CommissionRate":0.200,"ShopTypeId":2,"PeiSongType":"京东","InsertTime":"2017-12-27T10:44:25.463","url":"https://union-click.jd.com/jdc?d=7X5hvX","uid":"1000000078","pid":"1113721487","shopid":21519,"shijiancha":174},{"Id":21515,"ImgUrl":"http://img14.360buyimg.com/imgzone/jfs/t11290/78/885034002/263009/f35a704d/59fad177Nf7afc8f8.jpg","Name":"2017冬季新款加厚港风情侣面包服棉服 ","Introduce":"舒适柔软、简约风格、亲肤透气、微弹不变形","OldPrice":348.0000,"CouponMoney":80.0000,"CommissionRate":0.220,"ShopTypeId":2,"PeiSongType":"京东","InsertTime":"2017-12-27T10:44:25.46","url":"https://union-click.jd.com/jdc?d=B8Mc9v","uid":"1000000078","pid":"1113721487","shopid":21515,"shijiancha":174},{"Id":21516,"ImgUrl":"http://img14.360buyimg.com/imgzone/jfs/t12247/185/650807956/329516/dc730f92/5a105b0eNbd3b0676.jpg","Name":"【商场同款 官方正品】2017新品棉服男冬季棉袄","Introduce":"【内购价199 送运费险】天冷，这款棉服正合适，连帽加厚，保暖又有型！今天特价活动，限时抢","OldPrice":299.0000,"CouponMoney":100.0000,"CommissionRate":0.250,"ShopTypeId":2,"PeiSongType":"京东","InsertTime":"2017-12-27T10:44:25.46","url":"https://union-click.jd.com/jdc?d=OUm9YO","uid":"1000000078","pid":"1113721487","shopid":21516,"shijiancha":174},{"Id":21517,"ImgUrl":"http://img.jingtuitui.com/fa601201712261136085119.jpg","Name":" 花花公子毛衣男针织衫","Introduce":"爆款推荐！7300 好评！ 花花公子毛衣男针织衫","OldPrice":108.0000,"CouponMoney":59.0000,"CommissionRate":0.200,"ShopTypeId":2,"PeiSongType":"京东","InsertTime":"2017-12-27T10:44:25.46","url":"https://union-click.jd.com/jdc?d=ldQjJw","uid":"1000000078","pid":"1113721487","shopid":21517,"shijiancha":174},{"Id":21514,"ImgUrl":"http://img14.360buyimg.com/imgzone/jfs/t15229/98/1020840198/203589/e6115077/5a41fafcN932e7ae0.jpg","Name":"石末（SHIMO）夹克","Introduce":"什么时候我们已渐渐习惯被城市冰冷的钢筋水泥束缚住手脚？这个季节，掩藏不住内心的炽热，一起释放，一起出走吧！—— ——石末（SHIMO）夹克","OldPrice":758.0000,"CouponMoney":500.0000,"CommissionRate":0.200,"ShopTypeId":2,"PeiSongType":"京东","InsertTime":"2017-12-27T10:44:25.457","url":"https://union-click.jd.com/jdc?d=8BXPNA","uid":"1000000078","pid":"1113721487","shopid":21514,"shijiancha":174},{"Id":21513,"ImgUrl":"http://img14.360buyimg.com/imgzone/jfs/t12271/241/2488933604/263230/896b2d22/5a41f8b6Nee357dd9.jpg","Name":"石末（SHIMO）2017冬季新款高领呢子卫衣","Introduce":"什么时候我们已渐渐习惯被城市冰冷的钢筋水泥束缚住手脚？这个季节，掩藏不住内心的炽热，一起释放，一起出走吧！—— ——石末（SHIMO）卫衣","OldPrice":628.0000,"CouponMoney":410.0000,"CommissionRate":0.200,"ShopTypeId":2,"PeiSongType":"京东","InsertTime":"2017-12-27T10:44:25.453","url":"https://union-click.jd.com/jdc?d=JGNyoT","uid":"1000000078","pid":"1113721487","shopid":21513,"shijiancha":174},{"Id":21510,"ImgUrl":"http://img14.360buyimg.com/imgzone/jfs/t11251/285/1792444486/199890/719a4f12/5a097857Ne6466543.jpg","Name":"稻草人2017新款卫衣","Introduce":"稻草人2017秋冬季卫衣男连帽套头韩版潮运动上衣嘻哈纯色男士外套 冲量促销，立减60！","OldPrice":139.0000,"CouponMoney":60.0000,"CommissionRate":0.200,"ShopTypeId":2,"PeiSongType":"京东","InsertTime":"2017-12-27T10:44:25.447","url":"https://union-click.jd.com/jdc?d=x4UkJ0","uid":"1000000078","pid":"1113721487","shopid":21510,"shijiancha":174},{"Id":21511,"ImgUrl":"http://img14.360buyimg.com/imgzone/jfs/t12868/320/2499574144/703467/da0bb56d/5a41085dN7f5ee937.jpg","Name":"牛津纺长袖衬衫 有大码可穿200斤","Introduce":"免烫 ！不起球！纯色百搭衬衫  牛津纺长袖衬衫 有大码可穿200斤","OldPrice":89.0000,"CouponMoney":40.0000,"CommissionRate":0.300,"ShopTypeId":2,"PeiSongType":"京东","InsertTime":"2017-12-27T10:44:25.447","url":"https://union-click.jd.com/jdc?d=AHXEL3","uid":"1000000078","pid":"1113721487","shopid":21511,"shijiancha":174},{"Id":21506,"ImgUrl":"http://img14.360buyimg.com/imgzone/jfs/t8230/310/1606874652/265731/aad7b632/59bc5ba2N777f7a08.jpg","Name":"秋季新款修身印花开衫外套百搭休闲夹克","Introduce":"个性时尚的印花设计，做工精致。","OldPrice":199.0000,"CouponMoney":50.0000,"CommissionRate":0.220,"ShopTypeId":2,"PeiSongType":"京东","InsertTime":"2017-12-27T10:44:25.437","url":"https://union-click.jd.com/jdc?d=fK5Nz6","uid":"1000000078","pid":"1113721487","shopid":21506,"shijiancha":174},{"Id":21507,"ImgUrl":"http://img14.360buyimg.com/imgzone/jfs/t8737/171/1611373816/229259/37ea39c4/59bc5a94N1554bc8e.jpg","Name":"秋冬男款圆领秋季新毛衣针织线衫","Introduce":"拒绝冬天臃肿的款式，选择既保暖又修身的棉衣，选择针织衫更上档次，独特的设计，吸收国外的灵感，第一次使用针织衫设计中，优质的棉，更轻更暖更贴身\n","OldPrice":137.0000,"CouponMoney":30.0000,"CommissionRate":0.220,"ShopTypeId":2,"PeiSongType":"京东","InsertTime":"2017-12-27T10:44:25.437","url":"https://union-click.jd.com/jdc?d=fyQmBH","uid":"1000000078","pid":"1113721487","shopid":21507,"shijiancha":174},{"Id":21508,"ImgUrl":"http://img.jingtuitui.com/cbbce201712261608038237.jpg","Name":"【京东】商务休闲加绒加厚衬衫","Introduce":"舒适面料，优质里绒，不褪色，不掉绒，不起球，型男越冬，气质不减！\n","OldPrice":128.0000,"CouponMoney":59.0000,"CommissionRate":0.200,"ShopTypeId":2,"PeiSongType":"京东","InsertTime":"2017-12-27T10:44:25.437","url":"https://union-click.jd.com/jdc?d=nWbjm3","uid":"1000000078","pid":"1113721487","shopid":21508,"shijiancha":174},{"Id":21505,"ImgUrl":"http://img14.360buyimg.com/imgzone/jfs/t8008/156/1585106362/152949/9dda45de/59bc5f13N2df1e26f.jpg","Name":"新款商务男士牛仔裤男直筒宽松休闲","Introduce":"牛仔裤以其休闲自在而青春的渗透性，始终展现着一种自由随性的感觉，潮流文化泛滥的今天，牛仔裤仍然以其独特的姿态走在潮流前端，引领人们的着装风潮，诠释各种经典的时尚搭配风格。","OldPrice":116.0000,"CouponMoney":20.0000,"CommissionRate":0.220,"ShopTypeId":2,"PeiSongType":"京东","InsertTime":"2017-12-27T10:44:25.433","url":"https://union-click.jd.com/jdc?d=99jWkF","uid":"1000000078","pid":"1113721487","shopid":21505,"shijiancha":174},{"Id":21499,"ImgUrl":"http://img14.360buyimg.com/imgzone/jfs/t8506/38/1643812182/114875/fbb9bc59/59bcb1eaN9beb9114.jpg","Name":"胶源堂即使阿胶枣金丝枣","Introduce":"【大牌胶源堂】山东东阿即食水晶金丝枣，无核蜜枣单独小包装200g，券后9.9包邮，速度抢！","OldPrice":29.9000,"CouponMoney":20.0000,"CommissionRate":0.200,"ShopTypeId":6,"PeiSongType":"京东","InsertTime":"2017-12-27T10:44:25.33","url":"https://union-click.jd.com/jdc?d=6KnNBn","uid":"1000000078","pid":"1113721487","shopid":21499,"shijiancha":174},{"Id":21475,"ImgUrl":"http://img14.360buyimg.com/imgzone/jfs/t14866/288/321979001/355965/3490ea5d/5a29f32fNf7b08912.jpg","Name":"越南进口Jido鸡蛋面包干礼盒装390g","Introduce":"【第二件半价】【送礼佳品】 包装精美 老少皆宜的进口面包干\n","OldPrice":49.9000,"CouponMoney":20.0000,"CommissionRate":0.200,"ShopTypeId":6,"PeiSongType":"京东","InsertTime":"2017-12-27T10:44:25.293","url":"https://union-click.jd.com/jdc?d=nK07Rk","uid":"1000000078","pid":"1113721487","shopid":21475,"shijiancha":174},{"Id":21471,"ImgUrl":"http://img14.360buyimg.com/imgzone/jfs/t12616/201/914675507/55761/64c0b23f/5a166fc1N38697b29.jpg","Name":"波特酒原瓶原装进口红酒 PORTO加度 蒙特贝洛卡莱姆酒庄","Introduce":"波特酒 PORTO加度葡萄酒 卡莱姆酒庄 葡萄牙原瓶原装进口红酒 蒙特贝洛 茶色波特-750ml*1 \n葡萄牙国酒波特酒 卡莱姆酒庄 蒙特贝洛19度甜酒  领券立减25","OldPrice":98.0000,"CouponMoney":25.0000,"CommissionRate":0.220,"ShopTypeId":6,"PeiSongType":"京东","InsertTime":"2017-12-27T10:44:25.29","url":"https://union-click.jd.com/jdc?d=OBSkQp","uid":"1000000078","pid":"1113721487","shopid":21471,"shijiancha":174},{"Id":21459,"ImgUrl":"http://img14.360buyimg.com/imgzone/jfs/t9766/301/1121137340/173252/4f866107/59dc938fN7902cfe6.jpg","Name":"【京东商城】蒲江黄心猕猴桃30个装","Introduce":"超越11.11！超值30个装！每个1元不到  第二件再减5元！疯狂贱卖！错过的就后悔去吧！","OldPrice":39.9000,"CouponMoney":10.0000,"CommissionRate":0.200,"ShopTypeId":6,"PeiSongType":"京东","InsertTime":"2017-12-27T10:44:25.277","url":"https://union-click.jd.com/jdc?d=zSfbGT","uid":"1000000078","pid":"1113721487","shopid":21459,"shijiancha":174},{"Id":21453,"ImgUrl":"http://img14.360buyimg.com/imgzone/jfs/t13876/262/2225476323/220059/c3feda01/5a3b5f63N408ff620.jpg","Name":"【京仓直发】茅台醇香酒500ml*2","Introduce":"亏死算了！微信扫码每瓶998，现内购价2瓶才298，好喝不贵，礼盒包装，双旦送礼必备，让你面儿十足！","OldPrice":798.0000,"CouponMoney":500.0000,"CommissionRate":0.300,"ShopTypeId":6,"PeiSongType":"京东配送","InsertTime":"2017-12-27T10:44:25.27","url":"https://union-click.jd.com/jdc?d=QnyVz5","uid":"1000000078","pid":"1113721487","shopid":21453,"shijiancha":174},{"Id":21454,"ImgUrl":"http://img.jingtuitui.com/655b9201712270953459274.jpg","Name":"法国原瓶进口波尔多宾露酒庄干红葡萄酒红酒750ML*6瓶","Introduce":"波尔多法定产区AOC 13度干红 顶级的口感 赤霞珠，美乐，歌海娜的经典组合 成就了宾露酒庄干红这一款佳酿！自己喝和送人都非常棒！限时给力优惠，还送礼袋哦！","OldPrice":268.0000,"CouponMoney":100.0000,"CommissionRate":0.350,"ShopTypeId":6,"PeiSongType":"京东","InsertTime":"2017-12-27T10:44:25.27","url":"https://union-click.jd.com/jdc?d=weHZeV","uid":"1000000078","pid":"1113721487","shopid":21454,"shijiancha":174},{"Id":21446,"ImgUrl":"http://img.jingtuitui.com/341bd201712261332513982.jpg","Name":"LOVE百搭多用包头帽套头帽","Introduce":"多用途百搭套头帽可做帽子也可以做围脖，平时佩带，骑行佩带均可！","OldPrice":36.0000,"CouponMoney":17.0000,"CommissionRate":0.200,"ShopTypeId":3,"PeiSongType":"京东配送","InsertTime":"2017-12-27T10:44:24.137","url":"https://union-click.jd.com/jdc?d=PscMuH","uid":"1000000078","pid":"1113721487","shopid":21446,"shijiancha":174},{"Id":21445,"ImgUrl":"http://img.jingtuitui.com/35439201712261231113322.jpg","Name":"S925纯银耳环","Introduce":"【亏本促销】S925纯银耳环，不是真银不要钱，假一赔十，终身换新，代写贺卡\n","OldPrice":39.9000,"CouponMoney":24.0000,"CommissionRate":0.350,"ShopTypeId":3,"PeiSongType":"京东","InsertTime":"2017-12-27T10:44:24.133","url":"https://union-click.jd.com/jdc?d=isnBXZ","uid":"1000000078","pid":"1113721487","shopid":21445,"shijiancha":174},{"Id":21428,"ImgUrl":"http://img14.360buyimg.com/imgzone/jfs/t13240/282/1528054435/460898/115dbc43/5a220b65N056e95d0.jpg","Name":"锆石流苏耳线","Introduce":"女神款约会聚会时尚气质锆石925银流苏耳钉","OldPrice":39.9000,"CouponMoney":10.0000,"CommissionRate":0.300,"ShopTypeId":3,"PeiSongType":"京东","InsertTime":"2017-12-27T10:44:24.107","url":"https://union-click.jd.com/jdc?d=fB4NB0","uid":"1000000078","pid":"1113721487","shopid":21428,"shijiancha":174},{"Id":21422,"ImgUrl":"http://img14.360buyimg.com/imgzone/jfs/t16288/167/96853120/455312/78ded739/5a28bb4cN1d72134e.jpg","Name":"时尚太阳流苏耳线","Introduce":"京东品质，925纯银防过敏时尚大气女神款百搭耳线","OldPrice":39.9000,"CouponMoney":10.0000,"CommissionRate":0.300,"ShopTypeId":3,"PeiSongType":"京东","InsertTime":"2017-12-27T10:44:24.097","url":"https://union-click.jd.com/jdc?d=Ho4msu","uid":"1000000078","pid":"1113721487","shopid":21422,"shijiancha":174},{"Id":21423,"ImgUrl":"http://img14.360buyimg.com/imgzone/jfs/t13972/256/1396643345/417067/547036da/5a1fa013N10e673d6.jpg","Name":"冬季时尚太阳花锆石耳钉","Introduce":"送女友，送闺蜜，送朋友，京东品质，925银防过敏时尚大气耳钉","OldPrice":39.9000,"CouponMoney":20.0000,"CommissionRate":0.300,"ShopTypeId":3,"PeiSongType":"京东","InsertTime":"2017-12-27T10:44:24.097","url":"https://union-click.jd.com/jdc?d=5qh3xC","uid":"1000000078","pid":"1113721487","shopid":21423,"shijiancha":174},{"Id":21419,"ImgUrl":"http://img.jingtuitui.com/bf79c201712262040033054.jpg","Name":"S925纯银耳环","Introduce":"【亏本促销】S925纯银耳环，不是真银不要钱，假一赔十，终身换新，代写贺卡\n","OldPrice":39.9000,"CouponMoney":24.0000,"CommissionRate":0.350,"ShopTypeId":3,"PeiSongType":"京东","InsertTime":"2017-12-27T10:44:24.08","url":"https://union-click.jd.com/jdc?d=PsgDE4","uid":"1000000078","pid":"1113721487","shopid":21419,"shijiancha":174},{"Id":21418,"ImgUrl":"http://img14.360buyimg.com/imgzone/jfs/t7270/348/2612040217/228306/deeb843b/59b20466N5635ef35.jpg","Name":"俞兆林保暖内衣套装秋冬新款男士加绒加厚","Introduce":"俞兆林保暖内衣套装秋冬新款男士加绒加厚咖啡绒纯色全棉","OldPrice":119.0000,"CouponMoney":30.0000,"CommissionRate":0.200,"ShopTypeId":3,"PeiSongType":"京东","InsertTime":"2017-12-27T10:44:24.077","url":"https://union-click.jd.com/jdc?d=oUaIW3","uid":"1000000078","pid":"1113721487","shopid":21418,"shijiancha":174},{"Id":21416,"ImgUrl":"http://img14.360buyimg.com/imgzone/jfs/t6523/95/1089539849/251326/b0a5f897/594a14f9Nb8535eb0.jpg","Name":"珊瑚绒可爱浴帽洗澡吸水速干加厚干发帽","Introduce":"快速吸水  珊瑚绒可爱浴帽洗澡吸水速干加厚干发帽","OldPrice":23.9000,"CouponMoney":2.0000,"CommissionRate":0.200,"ShopTypeId":3,"PeiSongType":"京东","InsertTime":"2017-12-27T10:44:24.073","url":"https://union-click.jd.com/jdc?d=laWJdf","uid":"1000000078","pid":"1113721487","shopid":21416,"shijiancha":174},{"Id":21412,"ImgUrl":"http://img.jingtuitui.com/23e14201712181713413320.jpg","Name":"【暖冬必备】南极人加绒保暖内衣","Introduce":"人气爆款，几万好评！性价比之王，加厚黄金绒保暖套装，一套顶2套，迷恋，不如去拥有！","OldPrice":86.0000,"CouponMoney":27.0000,"CommissionRate":0.200,"ShopTypeId":3,"PeiSongType":"京东","InsertTime":"2017-12-27T10:44:24.067","url":"https://union-click.jd.com/jdc?d=U7g0Ws","uid":"1000000078","pid":"1113721487","shopid":21412,"shijiancha":174},{"Id":21409,"ImgUrl":"http://img.jingtuitui.com/ff7f2201712221158264747.jpg","Name":"2017冬新款棉服女韩版中长款时尚连帽修身羽绒服外套","Introduce":"修身连帽，印花，多种颜色可以选择，时候多种场合，简单而不失大方，温暖而不失漂亮","OldPrice":199.0000,"CouponMoney":40.0000,"CommissionRate":0.200,"ShopTypeId":1,"PeiSongType":"京东","InsertTime":"2017-12-27T10:44:23.83","url":"https://union-click.jd.com/jdc?d=IaGtm7","uid":"1000000078","pid":"1113721487","shopid":21409,"shijiancha":174},{"Id":21403,"ImgUrl":"http://img14.360buyimg.com/imgzone/jfs/t13486/252/581090167/280808/2fb9b6eb/5a0f1043Nd4ba9b78.jpg","Name":"可爱学院风棉衣保暖外套棉袄年底促销活动","Introduce":"小黄人贴布图案，多种2017年流行颜色可供选择，修身显瘦，大方。精于心简于形，是一款温暖而不失美丽的宝贝。","OldPrice":189.0000,"CouponMoney":20.0000,"CommissionRate":0.200,"ShopTypeId":1,"PeiSongType":"京东","InsertTime":"2017-12-27T10:44:23.823","url":"https://union-click.jd.com/jdc?d=9BzewT","uid":"1000000078","pid":"1113721487","shopid":21403,"shijiancha":174},{"Id":21398,"ImgUrl":"http://img.jingtuitui.com/498df201712261417078819.jpg","Name":"晨芙 200斤显瘦秋冬加绒加厚双排扣皮衣开衫","Introduce":"卷后直减50，更划算！ 性感立体翻领设计 袖口粒扣  皮质柔软，比普通的PU皮更有质感","OldPrice":298.0000,"CouponMoney":50.0000,"CommissionRate":0.200,"ShopTypeId":1,"PeiSongType":"京东","InsertTime":"2017-12-27T10:44:23.817","url":"https://union-click.jd.com/jdc?d=GqYfqQ","uid":"1000000078","pid":"1113721487","shopid":21398,"shijiancha":174},{"Id":21396,"ImgUrl":"http://img.jingtuitui.com/3130c201712261717442386.jpg","Name":"晨芙 中长款风衣秋冬胖mm200斤修身皮衣外套","Introduce":"2017秋冬新款，优质的PU面料加上精细的裁剪让皮衣穿着舒适，举手投足之间散发女人的魅力与气质","OldPrice":298.0000,"CouponMoney":50.0000,"CommissionRate":0.200,"ShopTypeId":1,"PeiSongType":"京东","InsertTime":"2017-12-27T10:44:23.813","url":"https://union-click.jd.com/jdc?d=T2ye9C","uid":"1000000078","pid":"1113721487","shopid":21396,"shijiancha":174},{"Id":21378,"ImgUrl":"http://img.jingtuitui.com/df36d201712261752124587.jpg","Name":"安吉拉毛绒玩具安抚布娃娃公仔【赠礼品袋】","Introduce":"metoo咪兔提拉米兔毛绒玩具兔子公仔婚庆礼品布娃娃女孩玩偶小号，手感舒适，卡通可爱，女友礼物。","OldPrice":55.0000,"CouponMoney":27.0000,"CommissionRate":0.200,"ShopTypeId":4,"PeiSongType":"京东配送","InsertTime":"2017-12-27T10:44:23.157","url":"https://union-click.jd.com/jdc?d=1wB2Ee","uid":"1000000078","pid":"1113721487","shopid":21378,"shijiancha":174},{"Id":21370,"ImgUrl":"http://img.jingtuitui.com/48db1201712261756542928.jpg","Name":"趴趴狗熊大号布娃娃公仔抱枕儿童玩偶","Introduce":"精细做工，高端材质，优等毛绒填充，弹性好蓬松度强，造型多变，不怕挤压，易洗快干，无毒无味，变身爱心狗，超级暖心哟~","OldPrice":59.0000,"CouponMoney":30.0000,"CommissionRate":0.200,"ShopTypeId":4,"PeiSongType":"京东","InsertTime":"2017-12-27T10:44:23.133","url":"https://union-click.jd.com/jdc?d=yyVcEM","uid":"1000000078","pid":"1113721487","shopid":21370,"shijiancha":174},{"Id":21366,"ImgUrl":"http://img.jingtuitui.com/ac929201712271002392883.jpg","Name":" 回力合金车模型和谐号动车组仿真高铁合金车组合玩具","Introduce":"仿真高铁，地铁合金车组合玩具，疯狂促销中，限时抢购！","OldPrice":58.0000,"CouponMoney":19.0000,"CommissionRate":0.200,"ShopTypeId":4,"PeiSongType":"京东","InsertTime":"2017-12-27T10:44:23.123","url":"https://union-click.jd.com/jdc?d=2dYvRM","uid":"1000000078","pid":"1113721487","shopid":21366,"shijiancha":174},{"Id":21325,"ImgUrl":"http://img.jingtuitui.com/c3813201712252044229928.jpg","Name":"儿童情绪管理 女孩课外阅读书籍  女生的小烦恼系列","Introduce":"【西班牙畅销书籍】没有谁天生就是笨笨的，每个人都能找到自己的闪光点，消除女孩成长过程中常有的自卑心理，令自己信心满满。","OldPrice":26.9000,"CouponMoney":17.0000,"CommissionRate":0.300,"ShopTypeId":10,"PeiSongType":"京东","InsertTime":"2017-12-26T15:51:07.74","url":"https://union-click.jd.com/jdc?d=pjVBmA","uid":"1000000078","pid":"1113721487","shopid":21325,"shijiancha":193},{"Id":21338,"ImgUrl":"http://img.jingtuitui.com/2da1a201712261123062424.jpg","Name":"【2片装】马力罗 iPhone7/6s/8钢化膜","Introduce":"都爱用这款，好膜，真的不贵！轻薄防爆，更耐用，无缝贴合，还原裸机之美！赶紧的，撸起来！","OldPrice":12.9000,"CouponMoney":7.0000,"CommissionRate":0.500,"ShopTypeId":11,"PeiSongType":"京东","InsertTime":"2017-12-26T15:51:07.497","url":"https://union-click.jd.com/jdc?d=SKDHJJ","uid":"1000000078","pid":"1113721487","shopid":21338,"shijiancha":193},{"Id":21320,"ImgUrl":"http://img14.360buyimg.com/imgzone/jfs/t12580/190/1920490002/276002/10825b94/5a2cfc55N492fec17.jpg","Name":"正版6本新编手指速算全套教材手指速算心算脑算","Introduce":"全新编纂6册套装，能有效的进行全脑潜能的开发，是其他速算的5-10倍。","OldPrice":33.8000,"CouponMoney":14.0000,"CommissionRate":0.200,"ShopTypeId":10,"PeiSongType":"京东","InsertTime":"2017-12-26T15:51:07.447","url":"https://union-click.jd.com/jdc?d=n15vWL","uid":"1000000078","pid":"1113721487","shopid":21320,"shijiancha":193}]